{
 "Susceptible": {
 "Drug": {
 "Amikacin": {
 "State": {
 "State": [ "N/A" ],
"percentage": [      100 ] 
},
"Gender": {
 "Gender": [ "Female", "Male", "Not recorded" ],
"percentage": [ 47.70318, 42.04947, 10.24735 ] 
},
"Age.Group": {
 "Age.Group": [ "0 to 2 Years", "13 to 18 Years", "19 to 64 Years", "3 to 12 Years", "65 to 84 Years", "85 and Over" ],
"percentage": [ 3.180212, 1.060071, 43.10954, 2.120141, 39.92933, 10.60071 ] 
},
"Speciality": {
 "Speciality": [ "Emergency Room", "General Unspecified ICU", "Medicine General", "Medicine ICU", "None Given", "Other", "Pediatric General", "Pediatric ICU", "Surgery General", "Surgery ICU" ],
"percentage": [ 15.90106, 1.060071, 40.63604, 11.66078, 6.360424, 1.413428, 1.766784, 1.413428, 13.78092, 6.007067 ] 
},
"Source": {
 "Source": [ "Bodily Fluids: Abdominal", "Bodily Fluids: Abscess / Pus", "Bodily Fluids: Bile", "Bodily Fluids: CSF", "Bodily Fluids: Exudate", "Bodily Fluids: Other", "Bodily Fluids: Peritoneal", "CVS: Blood", "GI: Abscess", "GI: Gall Bladder", "GI: Large Colon", "GI: Other", "GI: Pancreas", "GI: Rectum", "GI: Small Colon", "GU: Other", "GU: Prostate", "GU: Urinary Bladder", "GU: Urine", "Instruments: Drains / Tubes", "INT: Abscess", "INT: Decubitus", "INT: Other", "INT: Wound", "Respiratory", "Respiratory: Bronchials", "Respiratory: Bronchoalveolar lavage", "Respiratory: Endotracheal aspirate", "Respiratory: Other", "Respiratory: Sputum" ],
"percentage": [ 1.413428, 0.7067138, 1.060071, 0.3533569, 0.3533569, 0.3533569, 1.766784, 21.90813, 1.060071, 0.3533569, 1.413428, 2.473498, 0.7067138, 0.7067138, 0.7067138, 0.3533569, 0.3533569, 1.060071, 29.32862, 0.3533569, 1.060071, 0.3533569, 1.060071, 7.067138, 0.3533569, 2.120141, 1.060071, 4.946996, 1.766784, 13.42756 ] 
},
"In...Out.Patient": {
 "In...Out.Patient": [ "Inpatient", "None Given", "Outpatient" ],
"percentage": [ 76.32509, 7.773852, 15.90106 ] 
} 
},
"Amoxycillin clavulanate": {
 "State": {
 "State": [ "N/A" ],
"percentage": [      100 ] 
},
"Gender": {
 "Gender": [ "Female", "Male", "Not recorded" ],
"percentage": [ 50.54348, 40.21739,  9.23913 ] 
},
"Age.Group": {
 "Age.Group": [ "0 to 2 Years", "13 to 18 Years", "19 to 64 Years", "3 to 12 Years", "65 to 84 Years", "85 and Over" ],
"percentage": [ 3.804348, 1.630435, 43.47826, 2.173913, 39.13043, 9.782609 ] 
},
"Speciality": {
 "Speciality": [ "Emergency Room", "General Unspecified ICU", "Medicine General", "Medicine ICU", "None Given", "Other", "Pediatric General", "Pediatric ICU", "Surgery General", "Surgery ICU" ],
"percentage": [ 15.21739, 1.086957, 40.21739,  9.23913, 7.608696, 1.086957, 2.173913, 1.630435, 15.76087, 5.978261 ] 
},
"Source": {
 "Source": [ "Bodily Fluids: Abdominal", "Bodily Fluids: Abscess / Pus", "Bodily Fluids: Bile", "Bodily Fluids: Peritoneal", "CVS: Blood", "GI: Abscess", "GI: Gall Bladder", "GI: Large Colon", "GI: Other", "GI: Rectum", "GI: Small Colon", "GU: Other", "GU: Urinary Bladder", "GU: Urine", "Instruments: Drains / Tubes", "INT: Abscess", "INT: Decubitus", "INT: Other", "INT: Wound", "Respiratory", "Respiratory: Bronchials", "Respiratory: Bronchoalveolar lavage", "Respiratory: Endotracheal aspirate", "Respiratory: Other", "Respiratory: Sputum" ],
"percentage": [ 1.086957, 1.086957, 1.086957, 1.630435, 24.45652, 0.5434783, 0.5434783, 2.173913, 2.173913, 1.086957, 0.5434783, 0.5434783, 1.630435, 30.97826, 0.5434783, 1.086957, 0.5434783, 1.630435, 6.521739, 0.5434783, 2.173913, 1.086957, 4.347826, 1.630435, 10.32609 ] 
},
"In...Out.Patient": {
 "In...Out.Patient": [ "Inpatient", "None Given", "Outpatient" ],
"percentage": [ 76.08696, 8.695652, 15.21739 ] 
} 
},
"Ampicillin": {
 "State": {
 "State": [ "N/A" ],
"percentage": [      100 ] 
},
"Gender": {
 "Gender": [ "Female", "Male", "Not recorded" ],
"percentage": [ 49.42529, 36.78161,  13.7931 ] 
},
"Age.Group": {
 "Age.Group": [ "0 to 2 Years", "13 to 18 Years", "19 to 64 Years", "65 to 84 Years", "85 and Over" ],
"percentage": [ 4.597701, 2.298851, 44.82759, 41.37931, 6.896552 ] 
},
"Speciality": {
 "Speciality": [ "Emergency Room", "General Unspecified ICU", "Medicine General", "Medicine ICU", "None Given", "Pediatric General", "Pediatric ICU", "Surgery General", "Surgery ICU" ],
"percentage": [ 14.94253, 1.149425, 39.08046, 8.045977, 8.045977, 2.298851, 2.298851,  18.3908, 5.747126 ] 
},
"Source": {
 "Source": [ "Bodily Fluids: Abdominal", "Bodily Fluids: Abscess / Pus", "Bodily Fluids: Bile", "Bodily Fluids: Peritoneal", "CVS: Blood", "GI: Abscess", "GI: Large Colon", "GI: Other", "GI: Rectum", "GI: Small Colon", "GU: Other", "GU: Urinary Bladder", "GU: Urine", "Instruments: Drains / Tubes", "INT: Wound", "Respiratory: Bronchials", "Respiratory: Endotracheal aspirate", "Respiratory: Sputum" ],
"percentage": [ 1.149425, 1.149425, 1.149425, 1.149425, 26.43678, 1.149425, 2.298851, 1.149425, 1.149425, 1.149425, 1.149425, 1.149425, 29.88506, 1.149425, 11.49425, 1.149425, 5.747126, 10.34483 ] 
},
"In...Out.Patient": {
 "In...Out.Patient": [ "Inpatient", "None Given", "Outpatient" ],
"percentage": [ 77.01149, 8.045977, 14.94253 ] 
} 
},
"Aztreonam": {
 "State": {
 "State": [ "N/A" ],
"percentage": [      100 ] 
},
"Gender": {
 "Gender": [ "Female", "Male" ],
"percentage": [ 50.87719, 49.12281 ] 
},
"Age.Group": {
 "Age.Group": [ "0 to 2 Years", "13 to 18 Years", "19 to 64 Years", "3 to 12 Years", "65 to 84 Years", "85 and Over" ],
"percentage": [ 3.508772, 2.631579, 33.33333, 1.754386, 44.73684, 14.03509 ] 
},
"Speciality": {
 "Speciality": [ "Emergency Room", "General Unspecified ICU", "Medicine General", "Medicine ICU", "None Given", "Other", "Pediatric General", "Pediatric ICU", "Surgery General", "Surgery ICU" ],
"percentage": [ 10.52632, 2.631579, 49.12281, 13.15789, 2.631579, 3.508772, 2.631579, 2.631579, 7.017544, 6.140351 ] 
},
"Source": {
 "Source": [ "Bodily Fluids: Peritoneal", "CVS: Blood", "GI: Abscess", "GI: Large Colon", "GI: Other", "GI: Pancreas", "GI: Small Colon", "GU: Other", "GU: Urinary Bladder", "GU: Urine", "INT: Abscess", "INT: Decubitus", "INT: Other", "INT: Wound", "Respiratory: Bronchials", "Respiratory: Bronchoalveolar lavage", "Respiratory: Endotracheal aspirate", "Respiratory: Other", "Respiratory: Sputum" ],
"percentage": [ 2.631579, 10.52632, 2.631579, 1.754386, 5.263158, 1.754386, 1.754386, 0.877193, 1.754386, 23.68421, 2.631579, 0.877193, 1.754386, 7.894737, 2.631579, 2.631579, 10.52632, 1.754386, 16.66667 ] 
},
"In...Out.Patient": {
 "In...Out.Patient": [ "Inpatient", "None Given", "Outpatient" ],
"percentage": [ 83.33333, 6.140351, 10.52632 ] 
} 
},
"Cefepime": {
 "State": {
 "State": [ "N/A" ],
"percentage": [      100 ] 
},
"Gender": {
 "Gender": [ "Female", "Male", "Not recorded" ],
"percentage": [ 45.92275, 42.48927, 11.58798 ] 
},
"Age.Group": {
 "Age.Group": [ "0 to 2 Years", "13 to 18 Years", "19 to 64 Years", "3 to 12 Years", "65 to 84 Years", "85 and Over" ],
"percentage": [ 3.004292, 1.287554, 43.77682, 1.287554, 40.34335, 10.30043 ] 
},
"Speciality": {
 "Speciality": [ "Emergency Room", "General Unspecified ICU", "Medicine General", "Medicine ICU", "None Given", "Other", "Pediatric General", "Pediatric ICU", "Surgery General", "Surgery ICU" ],
"percentage": [ 15.45064, 1.287554, 41.20172, 10.72961, 6.437768, 1.716738, 1.716738, 1.287554, 14.16309, 6.008584 ] 
},
"Source": {
 "Source": [ "Bodily Fluids: Abdominal", "Bodily Fluids: Abscess / Pus", "Bodily Fluids: Bile", "Bodily Fluids: CSF", "Bodily Fluids: Exudate", "Bodily Fluids: Other", "Bodily Fluids: Peritoneal", "CVS: Blood", "GI: Abscess", "GI: Gall Bladder", "GI: Large Colon", "GI: Other", "GI: Pancreas", "GI: Rectum", "GI: Small Colon", "GU: Other", "GU: Prostate", "GU: Urinary Bladder", "GU: Urine", "Instruments: Drains / Tubes", "INT: Abscess", "INT: Decubitus", "INT: Other", "INT: Wound", "Respiratory: Bronchials", "Respiratory: Bronchoalveolar lavage", "Respiratory: Endotracheal aspirate", "Respiratory: Other", "Respiratory: Sputum" ],
"percentage": [ 1.287554, 0.8583691, 1.287554, 0.4291845, 0.4291845, 0.4291845, 1.287554, 23.17597, 1.287554, 0.4291845, 1.716738, 1.716738, 0.8583691, 0.8583691, 0.8583691, 0.4291845, 0.4291845, 1.287554, 27.03863, 0.4291845, 1.287554, 0.4291845, 0.8583691, 6.437768, 2.145923, 1.287554, 5.150215, 1.716738, 14.16309 ] 
},
"In...Out.Patient": {
 "In...Out.Patient": [ "Inpatient", "None Given", "Outpatient" ],
"percentage": [ 76.39485, 8.154506, 15.45064 ] 
} 
},
"Ceftaroline": {
 "State": {
 "State": [ "N/A" ],
"percentage": [      100 ] 
},
"Gender": {
 "Gender": [ "Female", "Male" ],
"percentage": [ 53.33333, 46.66667 ] 
},
"Age.Group": {
 "Age.Group": [ "0 to 2 Years", "13 to 18 Years", "19 to 64 Years", "65 to 84 Years", "85 and Over" ],
"percentage": [ 3.333333, 3.333333, 33.33333, 46.66667, 13.33333 ] 
},
"Speciality": {
 "Speciality": [ "Emergency Room", "General Unspecified ICU", "Medicine General", "Medicine ICU", "None Given", "Other", "Pediatric General", "Pediatric ICU", "Surgery General", "Surgery ICU" ],
"percentage": [ 11.11111, 3.333333, 51.11111, 11.11111, 3.333333, 3.333333, 1.111111, 3.333333, 5.555556, 6.666667 ] 
},
"Source": {
 "Source": [ "Bodily Fluids: Peritoneal", "CVS: Blood", "GI: Abscess", "GI: Large Colon", "GI: Other", "GI: Small Colon", "GU: Other", "GU: Urinary Bladder", "GU: Urine", "INT: Abscess", "INT: Decubitus", "INT: Other", "INT: Wound", "Respiratory: Bronchials", "Respiratory: Bronchoalveolar lavage", "Respiratory: Endotracheal aspirate", "Respiratory: Other", "Respiratory: Sputum" ],
"percentage": [ 2.222222, 12.22222, 2.222222, 2.222222, 4.444444, 2.222222, 1.111111, 2.222222, 22.22222, 3.333333, 1.111111, 1.111111, 7.777778, 2.222222, 3.333333, 11.11111, 2.222222, 16.66667 ] 
},
"In...Out.Patient": {
 "In...Out.Patient": [ "Inpatient", "None Given", "Outpatient" ],
"percentage": [ 82.22222, 6.666667, 11.11111 ] 
} 
},
"Ceftazidime": {
 "State": {
 "State": [ "N/A" ],
"percentage": [      100 ] 
},
"Gender": {
 "Gender": [ "Female", "Male", "Not recorded" ],
"percentage": [ 47.17742, 42.33871, 10.48387 ] 
},
"Age.Group": {
 "Age.Group": [ "0 to 2 Years", "13 to 18 Years", "19 to 64 Years", "3 to 12 Years", "65 to 84 Years", "85 and Over" ],
"percentage": [ 2.822581, 1.209677, 43.54839, 2.016129, 39.91935, 10.48387 ] 
},
"Speciality": {
 "Speciality": [ "Emergency Room", "General Unspecified ICU", "Medicine General", "Medicine ICU", "None Given", "Other", "Pediatric General", "Pediatric ICU", "Surgery General", "Surgery ICU" ],
"percentage": [ 16.12903, 1.209677, 39.91935, 12.09677, 6.451613, 1.209677, 2.016129, 1.209677, 14.51613, 5.241935 ] 
},
"Source": {
 "Source": [ "Bodily Fluids: Abdominal", "Bodily Fluids: Abscess / Pus", "Bodily Fluids: Bile", "Bodily Fluids: CSF", "Bodily Fluids: Exudate", "Bodily Fluids: Other", "Bodily Fluids: Peritoneal", "CVS: Blood", "GI: Abscess", "GI: Gall Bladder", "GI: Large Colon", "GI: Other", "GI: Pancreas", "GI: Rectum", "GI: Small Colon", "GU: Other", "GU: Urinary Bladder", "GU: Urine", "Instruments: Drains / Tubes", "INT: Abscess", "INT: Decubitus", "INT: Other", "INT: Wound", "Respiratory: Bronchials", "Respiratory: Bronchoalveolar lavage", "Respiratory: Endotracheal aspirate", "Respiratory: Other", "Respiratory: Sputum" ],
"percentage": [ 1.612903, 0.8064516, 1.209677, 0.4032258, 0.4032258, 0.4032258, 1.612903, 22.58065, 1.612903, 0.4032258, 1.612903, 2.419355, 0.8064516, 0.8064516, 0.8064516, 0.4032258, 1.209677,  26.6129, 0.4032258, 1.209677, 0.4032258, 1.209677, 6.854839, 2.419355, 1.209677,  4.83871, 1.612903,  14.1129 ] 
},
"In...Out.Patient": {
 "In...Out.Patient": [ "Inpatient", "None Given", "Outpatient" ],
"percentage": [ 76.20968,  7.66129, 16.12903 ] 
} 
},
"Ceftazidime avibactam": {
 "State": {
 "State": [ "N/A" ],
"percentage": [      100 ] 
},
"Gender": {
 "Gender": [ "Female", "Male" ],
"percentage": [ 52.17391, 47.82609 ] 
},
"Age.Group": {
 "Age.Group": [ "0 to 2 Years", "13 to 18 Years", "19 to 64 Years", "3 to 12 Years", "65 to 84 Years", "85 and Over" ],
"percentage": [ 4.347826, 2.173913, 35.50725, 2.173913, 42.02899, 13.76812 ] 
},
"Speciality": {
 "Speciality": [ "Emergency Room", "General Unspecified ICU", "Medicine General", "Medicine ICU", "None Given", "Other", "Pediatric General", "Pediatric ICU", "Surgery General", "Surgery ICU" ],
"percentage": [  11.5942, 2.173913, 48.55072, 13.76812, 2.173913, 2.898551, 2.173913, 2.898551, 7.971014, 5.797101 ] 
},
"Source": {
 "Source": [ "Bodily Fluids: Peritoneal", "CVS: Blood", "GI: Abscess", "GI: Large Colon", "GI: Other", "GI: Pancreas", "GI: Small Colon", "GU: Other", "GU: Urinary Bladder", "GU: Urine", "INT: Abscess", "INT: Decubitus", "INT: Other", "INT: Wound", "Respiratory: Bronchials", "Respiratory: Bronchoalveolar lavage", "Respiratory: Endotracheal aspirate", "Respiratory: Other", "Respiratory: Sputum" ],
"percentage": [ 2.173913,  9.42029, 2.898551, 1.449275, 5.072464, 1.449275, 1.449275, 0.7246377, 1.449275, 28.98551, 2.173913, 0.7246377, 1.449275, 8.695652, 2.173913, 2.173913, 10.14493, 1.449275, 15.94203 ] 
},
"In...Out.Patient": {
 "In...Out.Patient": [ "Inpatient", "None Given", "Outpatient" ],
"percentage": [ 83.33333, 5.072464,  11.5942 ] 
} 
},
"Ceftriaxone": {
 "State": {
 "State": [ "N/A" ],
"percentage": [      100 ] 
},
"Gender": {
 "Gender": [ "Female", "Male", "Not recorded" ],
"percentage": [ 41.40625,     37.5, 21.09375 ] 
},
"Age.Group": {
 "Age.Group": [ "0 to 2 Years", "19 to 64 Years", "3 to 12 Years", "65 to 84 Years", "85 and Over" ],
"percentage": [  2.34375, 50.78125,  2.34375,     37.5,  7.03125 ] 
},
"Speciality": {
 "Speciality": [ "Emergency Room", "Medicine General", "Medicine ICU", "None Given", "Pediatric General", "Surgery General", "Surgery ICU" ],
"percentage": [  20.3125,  32.8125,    9.375,    9.375,   1.5625, 21.09375,  5.46875 ] 
},
"Source": {
 "Source": [ "Bodily Fluids: Abdominal", "Bodily Fluids: Abscess / Pus", "Bodily Fluids: Bile", "Bodily Fluids: CSF", "Bodily Fluids: Exudate", "Bodily Fluids: Other", "Bodily Fluids: Peritoneal", "CVS: Blood", "GI: Gall Bladder", "GI: Large Colon", "GI: Rectum", "GU: Prostate", "GU: Urinary Bladder", "GU: Urine", "Instruments: Drains / Tubes", "INT: Other", "INT: Wound", "Respiratory: Bronchials", "Respiratory: Other", "Respiratory: Sputum" ],
"percentage": [  2.34375,   1.5625,  2.34375,  0.78125,  0.78125,  0.78125,  0.78125, 33.59375,  0.78125,   1.5625,   1.5625,  0.78125,  0.78125,  29.6875,  0.78125,  0.78125,  5.46875,   1.5625,   1.5625, 11.71875 ] 
},
"In...Out.Patient": {
 "In...Out.Patient": [ "Inpatient", "None Given", "Outpatient" ],
"percentage": [  70.3125,    9.375,  20.3125 ] 
} 
},
"Doripenem": {
 "State": {
 "State": [ "N/A" ],
"percentage": [      100 ] 
},
"Gender": {
 "Gender": [ "Female", "Male" ],
"percentage": [ 51.82482, 48.17518 ] 
},
"Age.Group": {
 "Age.Group": [ "0 to 2 Years", "13 to 18 Years", "19 to 64 Years", "3 to 12 Years", "65 to 84 Years", "85 and Over" ],
"percentage": [ 4.379562, 2.189781,  35.0365, 2.189781, 42.33577, 13.86861 ] 
},
"Speciality": {
 "Speciality": [ "Emergency Room", "General Unspecified ICU", "Medicine General", "Medicine ICU", "None Given", "Other", "Pediatric General", "Pediatric ICU", "Surgery General", "Surgery ICU" ],
"percentage": [ 11.67883, 2.189781, 48.17518, 13.86861, 2.189781, 2.919708, 2.189781, 2.919708, 8.029197, 5.839416 ] 
},
"Source": {
 "Source": [ "Bodily Fluids: Peritoneal", "CVS: Blood", "GI: Abscess", "GI: Large Colon", "GI: Other", "GI: Pancreas", "GI: Small Colon", "GU: Other", "GU: Urinary Bladder", "GU: Urine", "INT: Abscess", "INT: Decubitus", "INT: Other", "INT: Wound", "Respiratory: Bronchials", "Respiratory: Bronchoalveolar lavage", "Respiratory: Endotracheal aspirate", "Respiratory: Other", "Respiratory: Sputum" ],
"percentage": [ 2.189781, 9.489051, 2.919708, 1.459854, 5.109489, 1.459854, 1.459854, 0.729927, 1.459854, 28.46715, 2.189781, 0.729927, 1.459854, 8.759124, 2.189781, 2.189781, 10.21898, 1.459854, 16.05839 ] 
},
"In...Out.Patient": {
 "In...Out.Patient": [ "Inpatient", "None Given", "Outpatient" ],
"percentage": [ 83.21168, 5.109489, 11.67883 ] 
} 
},
"Imipenem": {
 "State": {
 "State": [ "N/A" ],
"percentage": [      100 ] 
},
"Gender": {
 "Gender": [ "Female", "Male" ],
"percentage": [ 51.82482, 48.17518 ] 
},
"Age.Group": {
 "Age.Group": [ "0 to 2 Years", "13 to 18 Years", "19 to 64 Years", "3 to 12 Years", "65 to 84 Years", "85 and Over" ],
"percentage": [ 4.379562, 2.189781,  35.0365, 2.189781, 42.33577, 13.86861 ] 
},
"Speciality": {
 "Speciality": [ "Emergency Room", "General Unspecified ICU", "Medicine General", "Medicine ICU", "None Given", "Other", "Pediatric General", "Pediatric ICU", "Surgery General", "Surgery ICU" ],
"percentage": [ 11.67883, 2.189781, 48.17518, 13.86861, 2.189781, 2.919708, 2.189781, 2.919708, 8.029197, 5.839416 ] 
},
"Source": {
 "Source": [ "Bodily Fluids: Peritoneal", "CVS: Blood", "GI: Abscess", "GI: Large Colon", "GI: Other", "GI: Pancreas", "GI: Small Colon", "GU: Other", "GU: Urinary Bladder", "GU: Urine", "INT: Abscess", "INT: Decubitus", "INT: Other", "INT: Wound", "Respiratory: Bronchials", "Respiratory: Bronchoalveolar lavage", "Respiratory: Endotracheal aspirate", "Respiratory: Other", "Respiratory: Sputum" ],
"percentage": [ 2.189781, 9.489051, 2.919708, 1.459854, 5.109489, 1.459854, 1.459854, 0.729927, 1.459854, 28.46715, 2.189781, 0.729927, 1.459854, 8.759124, 2.189781, 2.189781, 10.21898, 1.459854, 16.05839 ] 
},
"In...Out.Patient": {
 "In...Out.Patient": [ "Inpatient", "None Given", "Outpatient" ],
"percentage": [ 83.21168, 5.109489, 11.67883 ] 
} 
},
"Levofloxacin": {
 "State": {
 "State": [ "N/A" ],
"percentage": [      100 ] 
},
"Gender": {
 "Gender": [ "Female", "Male", "Not recorded" ],
"percentage": [ 47.61905, 41.26984, 11.11111 ] 
},
"Age.Group": {
 "Age.Group": [ "0 to 2 Years", "13 to 18 Years", "19 to 64 Years", "3 to 12 Years", "65 to 84 Years", "85 and Over" ],
"percentage": [ 4.232804, 1.587302, 46.03175, 1.058201, 36.50794, 10.58201 ] 
},
"Speciality": {
 "Speciality": [ "Emergency Room", "General Unspecified ICU", "Medicine General", "Medicine ICU", "None Given", "Other", "Pediatric General", "Pediatric ICU", "Surgery General", "Surgery ICU" ],
"percentage": [ 13.22751, 1.587302, 38.62434, 12.16931, 8.465608, 1.587302, 2.116402, 2.116402, 14.28571, 5.820106 ] 
},
"Source": {
 "Source": [ "Bodily Fluids: Abdominal", "Bodily Fluids: Abscess / Pus", "Bodily Fluids: Bile", "Bodily Fluids: CSF", "Bodily Fluids: Exudate", "Bodily Fluids: Other", "Bodily Fluids: Peritoneal", "CVS: Blood", "GI: Abscess", "GI: Gall Bladder", "GI: Large Colon", "GI: Other", "GI: Pancreas", "GI: Rectum", "GU: Urinary Bladder", "GU: Urine", "Instruments: Drains / Tubes", "INT: Abscess", "INT: Other", "INT: Wound", "Respiratory: Bronchials", "Respiratory: Bronchoalveolar lavage", "Respiratory: Endotracheal aspirate", "Respiratory: Other", "Respiratory: Sputum" ],
"percentage": [ 1.587302, 1.058201, 1.058201, 0.5291005, 0.5291005, 0.5291005, 1.587302, 21.69312, 0.5291005, 0.5291005, 1.587302, 2.645503, 0.5291005, 0.5291005, 1.587302, 24.86772, 0.5291005, 0.5291005, 1.058201, 8.994709, 1.587302, 1.587302, 5.820106, 2.116402, 16.40212 ] 
},
"In...Out.Patient": {
 "In...Out.Patient": [ "Inpatient", "None Given", "Outpatient" ],
"percentage": [ 76.71958, 10.05291, 13.22751 ] 
} 
},
"Meropenem": {
 "State": {
 "State": [ "N/A" ],
"percentage": [      100 ] 
},
"Gender": {
 "Gender": [ "Female", "Male", "Not recorded" ],
"percentage": [ 47.51773, 42.19858, 10.28369 ] 
},
"Age.Group": {
 "Age.Group": [ "0 to 2 Years", "13 to 18 Years", "19 to 64 Years", "3 to 12 Years", "65 to 84 Years", "85 and Over" ],
"percentage": [ 3.191489,  1.06383,  42.9078,  2.12766, 40.07092,  10.6383 ] 
},
"Speciality": {
 "Speciality": [ "Emergency Room", "General Unspecified ICU", "Medicine General", "Medicine ICU", "None Given", "Other", "Pediatric General", "Pediatric ICU", "Surgery General", "Surgery ICU" ],
"percentage": [ 15.95745,  1.06383, 40.07092, 12.05674, 6.382979,  1.41844,  1.77305,  1.41844, 13.82979, 6.028369 ] 
},
"Source": {
 "Source": [ "Bodily Fluids: Abdominal", "Bodily Fluids: Abscess / Pus", "Bodily Fluids: Bile", "Bodily Fluids: CSF", "Bodily Fluids: Exudate", "Bodily Fluids: Other", "Bodily Fluids: Peritoneal", "CVS: Blood", "GI: Abscess", "GI: Gall Bladder", "GI: Large Colon", "GI: Other", "GI: Pancreas", "GI: Rectum", "GI: Small Colon", "GU: Other", "GU: Prostate", "GU: Urinary Bladder", "GU: Urine", "Instruments: Drains / Tubes", "INT: Abscess", "INT: Decubitus", "INT: Other", "INT: Wound", "Respiratory", "Respiratory: Bronchials", "Respiratory: Bronchoalveolar lavage", "Respiratory: Endotracheal aspirate", "Respiratory: Other", "Respiratory: Sputum" ],
"percentage": [  1.41844, 0.7092199,  1.06383, 0.3546099, 0.3546099, 0.3546099,  1.77305, 21.98582,  1.41844, 0.3546099,  1.41844,  2.48227, 0.7092199, 0.7092199, 0.7092199, 0.3546099, 0.3546099,  1.06383,  28.7234, 0.3546099,  1.06383, 0.3546099,  1.06383, 7.092199, 0.3546099,  2.12766,  1.06383, 4.964539,  1.77305, 13.47518 ] 
},
"In...Out.Patient": {
 "In...Out.Patient": [ "Inpatient", "None Given", "Outpatient" ],
"percentage": [ 76.24113, 7.801418, 15.95745 ] 
} 
},
"Minocycline": {
 "State": {
 "State": [ "N/A" ],
"percentage": [      100 ] 
},
"Gender": {
 "Gender": [ "Female", "Male", "Not recorded" ],
"percentage": [ 44.53125, 36.71875,    18.75 ] 
},
"Age.Group": {
 "Age.Group": [ "0 to 2 Years", "19 to 64 Years", "3 to 12 Years", "65 to 84 Years", "85 and Over" ],
"percentage": [  2.34375, 50.78125,   1.5625, 36.71875,  8.59375 ] 
},
"Speciality": {
 "Speciality": [ "Emergency Room", "Medicine General", "Medicine ICU", "None Given", "Pediatric General", "Surgery General", "Surgery ICU" ],
"percentage": [ 19.53125, 35.15625, 10.15625,  8.59375,   1.5625, 19.53125,  5.46875 ] 
},
"Source": {
 "Source": [ "Bodily Fluids: Abdominal", "Bodily Fluids: Abscess / Pus", "Bodily Fluids: Bile", "Bodily Fluids: CSF", "Bodily Fluids: Other", "Bodily Fluids: Peritoneal", "CVS: Blood", "GI: Gall Bladder", "GI: Large Colon", "GI: Rectum", "GU: Prostate", "GU: Urinary Bladder", "GU: Urine", "Instruments: Drains / Tubes", "INT: Other", "INT: Wound", "Respiratory", "Respiratory: Bronchials", "Respiratory: Other", "Respiratory: Sputum" ],
"percentage": [    3.125,  0.78125,  2.34375,  0.78125,  0.78125,   1.5625,  32.8125,  0.78125,   1.5625,   1.5625,  0.78125,  0.78125, 30.46875,  0.78125,  0.78125,  5.46875,  0.78125,   1.5625,   1.5625,  10.9375 ] 
},
"In...Out.Patient": {
 "In...Out.Patient": [ "Inpatient", "None Given", "Outpatient" ],
"percentage": [   71.875,  8.59375, 19.53125 ] 
} 
},
"Piperacillin tazobactam": {
 "State": {
 "State": [ "N/A" ],
"percentage": [      100 ] 
},
"Gender": {
 "Gender": [ "Female", "Male", "Not recorded" ],
"percentage": [ 48.01587, 41.26984, 10.71429 ] 
},
"Age.Group": {
 "Age.Group": [ "0 to 2 Years", "13 to 18 Years", "19 to 64 Years", "3 to 12 Years", "65 to 84 Years", "85 and Over" ],
"percentage": [ 3.571429, 1.190476, 43.25397, 1.984127, 39.68254, 10.31746 ] 
},
"Speciality": {
 "Speciality": [ "Emergency Room", "General Unspecified ICU", "Medicine General", "Medicine ICU", "None Given", "Other", "Pediatric General", "Pediatric ICU", "Surgery General", "Surgery ICU" ],
"percentage": [ 15.07937, 1.190476, 40.07937, 10.71429, 6.349206, 1.587302, 1.984127, 1.587302, 15.07937, 6.349206 ] 
},
"Source": {
 "Source": [ "Bodily Fluids: Abdominal", "Bodily Fluids: Abscess / Pus", "Bodily Fluids: Bile", "Bodily Fluids: CSF", "Bodily Fluids: Exudate", "Bodily Fluids: Other", "Bodily Fluids: Peritoneal", "CVS: Blood", "GI: Abscess", "GI: Gall Bladder", "GI: Large Colon", "GI: Other", "GI: Pancreas", "GI: Rectum", "GI: Small Colon", "GU: Other", "GU: Prostate", "GU: Urinary Bladder", "GU: Urine", "Instruments: Drains / Tubes", "INT: Abscess", "INT: Decubitus", "INT: Other", "INT: Wound", "Respiratory", "Respiratory: Bronchials", "Respiratory: Bronchoalveolar lavage", "Respiratory: Endotracheal aspirate", "Respiratory: Other", "Respiratory: Sputum" ],
"percentage": [ 1.190476, 0.7936508, 0.7936508, 0.3968254, 0.3968254, 0.3968254, 1.190476, 22.61905, 0.7936508, 0.3968254, 1.587302, 1.984127, 0.3968254, 0.7936508, 0.7936508, 0.3968254, 0.3968254, 1.190476, 30.95238, 0.3968254, 1.190476, 0.3968254, 1.190476, 7.539683, 0.3968254, 1.587302, 1.190476,  5.15873, 1.984127, 11.50794 ] 
},
"In...Out.Patient": {
 "In...Out.Patient": [ "Inpatient", "None Given", "Outpatient" ],
"percentage": [ 76.98413, 7.936508, 15.07937 ] 
} 
},
"Tigecycline": {
 "State": {
 "State": [ "N/A" ],
"percentage": [      100 ] 
},
"Gender": {
 "Gender": [ "Female", "Male", "Not recorded" ],
"percentage": [ 47.88732, 41.90141, 10.21127 ] 
},
"Age.Group": {
 "Age.Group": [ "0 to 2 Years", "13 to 18 Years", "19 to 64 Years", "3 to 12 Years", "65 to 84 Years", "85 and Over" ],
"percentage": [ 3.169014, 1.056338, 43.30986, 2.112676, 39.78873, 10.56338 ] 
},
"Speciality": {
 "Speciality": [ "Emergency Room", "General Unspecified ICU", "Medicine General", "Medicine ICU", "None Given", "Other", "Pediatric General", "Pediatric ICU", "Surgery General", "Surgery ICU" ],
"percentage": [ 15.84507, 1.056338, 40.49296, 11.97183, 6.338028, 1.408451, 1.760563, 1.408451, 13.73239, 5.985915 ] 
},
"Source": {
 "Source": [ "Bodily Fluids: Abdominal", "Bodily Fluids: Abscess / Pus", "Bodily Fluids: Bile", "Bodily Fluids: CSF", "Bodily Fluids: Exudate", "Bodily Fluids: Other", "Bodily Fluids: Peritoneal", "CVS: Blood", "GI: Abscess", "GI: Gall Bladder", "GI: Large Colon", "GI: Other", "GI: Pancreas", "GI: Rectum", "GI: Small Colon", "GU: Other", "GU: Prostate", "GU: Urinary Bladder", "GU: Urine", "Instruments: Drains / Tubes", "INT: Abscess", "INT: Decubitus", "INT: Other", "INT: Wound", "Respiratory", "Respiratory: Bronchials", "Respiratory: Bronchoalveolar lavage", "Respiratory: Endotracheal aspirate", "Respiratory: Other", "Respiratory: Sputum" ],
"percentage": [ 1.408451, 0.7042254, 1.056338, 0.3521127, 0.3521127, 0.3521127, 1.760563, 21.83099, 1.408451, 0.3521127, 1.408451, 2.464789, 0.7042254, 0.7042254, 0.7042254, 0.3521127, 0.3521127, 1.056338, 29.22535, 0.3521127, 1.056338, 0.3521127, 1.056338, 7.042254, 0.3521127, 2.112676, 1.056338, 4.929577, 1.760563, 13.38028 ] 
},
"In...Out.Patient": {
 "In...Out.Patient": [ "Inpatient", "None Given", "Outpatient" ],
"percentage": [ 76.40845, 7.746479, 15.84507 ] 
} 
} 
},
"percentage": [ 9.711736, 6.314345, 2.985587, 3.912148, 7.995882, 3.088538, 8.510638, 4.735758, 4.392588, 4.701441, 4.701441,  6.48593, 9.677419, 4.392588, 8.647907, 9.746054 ],
"weight": 0.8236292,
"backgroundColor": [ "#a6cee3", "#1f78b4", "#b2df8a", "#ccebc5", "#fb9a99", "#d95f02", "#fdbf6f", "#e7298a", "#ff7f00", "#e41a1c", "#b15928", "#8dd3c7", "#bebada", "#80b1d3", "#b3de69", "#fccde5" ] 
},
"Intermediate": {
 "Drug": {
 "Amoxycillin clavulanate": {
 "State": {
 "State": [ "N/A" ],
"percentage": [      100 ] 
},
"Gender": {
 "Gender": [ "Female", "Male", "Not recorded" ],
"percentage": [       40, 43.63636, 16.36364 ] 
},
"Age.Group": {
 "Age.Group": [ "0 to 2 Years", "19 to 64 Years", "65 to 84 Years", "85 and Over" ],
"percentage": [ 3.636364, 45.45455,       40, 10.90909 ] 
},
"Speciality": {
 "Speciality": [ "Emergency Room", "Medicine General", "Medicine ICU", "None Given", "Other", "Pediatric General", "Pediatric ICU", "Surgery General", "Surgery ICU" ],
"percentage": [ 18.18182,       40, 16.36364, 1.818182, 1.818182, 1.818182, 1.818182, 12.72727, 5.454545 ] 
},
"Source": {
 "Source": [ "Bodily Fluids: Abdominal", "Bodily Fluids: CSF", "Bodily Fluids: Exudate", "Bodily Fluids: Other", "CVS: Blood", "GI: Abscess", "GI: Other", "GI: Pancreas", "GU: Urine", "INT: Abscess", "INT: Wound", "Respiratory: Bronchoalveolar lavage", "Respiratory: Endotracheal aspirate", "Respiratory: Other", "Respiratory: Sputum" ],
"percentage": [ 1.818182, 1.818182, 1.818182, 1.818182, 16.36364, 1.818182, 1.818182, 1.818182, 29.09091, 1.818182, 10.90909, 1.818182, 7.272727, 3.636364, 16.36364 ] 
},
"In...Out.Patient": {
 "In...Out.Patient": [ "Inpatient", "None Given", "Outpatient" ],
"percentage": [ 78.18182, 3.636364, 18.18182 ] 
} 
},
"Ampicillin": {
 "State": {
 "State": [ "N/A" ],
"percentage": [      100 ] 
},
"Gender": {
 "Gender": [ "Female", "Not recorded" ],
"percentage": [       50,       50 ] 
},
"Age.Group": {
 "Age.Group": [ "19 to 64 Years", "65 to 84 Years" ],
"percentage": [       50,       50 ] 
},
"Speciality": {
 "Speciality": [ "Medicine ICU", "None Given" ],
"percentage": [       50,       50 ] 
},
"Source": {
 "Source": [ "CVS: Blood", "INT: Wound" ],
"percentage": [       50,       50 ] 
},
"In...Out.Patient": {
 "In...Out.Patient": [ "Inpatient", "None Given" ],
"percentage": [       50,       50 ] 
} 
},
"Aztreonam": {
 "State": {
 "State": [ "N/A" ],
"percentage": [      100 ] 
},
"Gender": {
 "Gender": [ "Female" ],
"percentage": [      100 ] 
},
"Age.Group": {
 "Age.Group": [ "19 to 64 Years", "85 and Over" ],
"percentage": [ 66.66667, 33.33333 ] 
},
"Speciality": {
 "Speciality": [ "Emergency Room", "Medicine General", "Medicine ICU" ],
"percentage": [ 33.33333, 33.33333, 33.33333 ] 
},
"Source": {
 "Source": [ "GI: Abscess", "GU: Urine" ],
"percentage": [ 33.33333, 66.66667 ] 
},
"In...Out.Patient": {
 "In...Out.Patient": [ "Inpatient", "Outpatient" ],
"percentage": [ 66.66667, 33.33333 ] 
} 
},
"Cefepime": {
 "State": {
 "State": [ "N/A" ],
"percentage": [      100 ] 
},
"Gender": {
 "Gender": [ "Female", "Male" ],
"percentage": [ 33.33333, 66.66667 ] 
},
"Age.Group": {
 "Age.Group": [ "19 to 64 Years", "3 to 12 Years", "65 to 84 Years", "85 and Over" ],
"percentage": [       20, 13.33333,       60, 6.666667 ] 
},
"Speciality": {
 "Speciality": [ "Emergency Room", "Medicine General", "Medicine ICU", "None Given", "Pediatric General", "Surgery General", "Surgery ICU" ],
"percentage": [ 6.666667, 33.33333,       20, 6.666667, 6.666667,       20, 6.666667 ] 
},
"Source": {
 "Source": [ "Bodily Fluids: Peritoneal", "CVS: Blood", "GI: Other", "GU: Urine", "INT: Other", "INT: Wound", "Respiratory: Endotracheal aspirate" ],
"percentage": [ 13.33333,       20, 6.666667,       40, 6.666667, 6.666667, 6.666667 ] 
},
"In...Out.Patient": {
 "In...Out.Patient": [ "Inpatient", "None Given", "Outpatient" ],
"percentage": [ 86.66667, 6.666667, 6.666667 ] 
} 
},
"Ceftaroline": {
 "State": {
 "State": [ "N/A" ],
"percentage": [      100 ] 
},
"Gender": {
 "Gender": [ "Female", "Male" ],
"percentage": [       50,       50 ] 
},
"Age.Group": {
 "Age.Group": [ "0 to 2 Years", "19 to 64 Years", "65 to 84 Years", "85 and Over" ],
"percentage": [       25,       25,       25,       25 ] 
},
"Speciality": {
 "Speciality": [ "Emergency Room", "Medicine General", "Pediatric General" ],
"percentage": [       25,       50,       25 ] 
},
"Source": {
 "Source": [ "GI: Abscess", "GU: Urine", "Respiratory: Sputum" ],
"percentage": [       25,       25,       50 ] 
},
"In...Out.Patient": {
 "In...Out.Patient": [ "Inpatient", "Outpatient" ],
"percentage": [       75,       25 ] 
} 
},
"Ceftazidime": {
 "State": {
 "State": [ "N/A" ],
"percentage": [      100 ] 
},
"Gender": {
 "Gender": [ "Female", "Male", "Not recorded" ],
"percentage": [       40,       40,       20 ] 
},
"Age.Group": {
 "Age.Group": [ "65 to 84 Years", "85 and Over" ],
"percentage": [       80,       20 ] 
},
"Speciality": {
 "Speciality": [ "Medicine General", "Surgery ICU" ],
"percentage": [       60,       40 ] 
},
"Source": {
 "Source": [ "CVS: Blood", "GU: Prostate", "GU: Urine" ],
"percentage": [       40,       20,       40 ] 
},
"In...Out.Patient": {
 "In...Out.Patient": [ "Inpatient" ],
"percentage": [      100 ] 
} 
},
"Imipenem": {
 "State": {
 "State": [ "N/A" ],
"percentage": [      100 ] 
},
"Gender": {
 "Gender": [ "Female" ],
"percentage": [      100 ] 
},
"Age.Group": {
 "Age.Group": [ "19 to 64 Years" ],
"percentage": [      100 ] 
},
"Speciality": {
 "Speciality": [ "Medicine General" ],
"percentage": [      100 ] 
},
"Source": {
 "Source": [ "GU: Urine" ],
"percentage": [      100 ] 
},
"In...Out.Patient": {
 "In...Out.Patient": [ "Inpatient" ],
"percentage": [      100 ] 
} 
},
"Levofloxacin": {
 "State": {
 "State": [ "N/A" ],
"percentage": [      100 ] 
},
"Gender": {
 "Gender": [ "Female", "Male", "Not recorded" ],
"percentage": [ 38.46154, 46.15385, 15.38462 ] 
},
"Age.Group": {
 "Age.Group": [ "19 to 64 Years", "65 to 84 Years", "85 and Over" ],
"percentage": [ 30.76923, 53.84615, 15.38462 ] 
},
"Speciality": {
 "Speciality": [ "Emergency Room", "Medicine General", "Medicine ICU", "None Given", "Surgery General", "Surgery ICU" ],
"percentage": [ 23.07692, 23.07692, 15.38462, 7.692308, 23.07692, 7.692308 ] 
},
"Source": {
 "Source": [ "Bodily Fluids: Abdominal", "Bodily Fluids: Bile", "CVS: Blood", "GU: Prostate", "GU: Urine", "INT: Wound", "Respiratory: Bronchials", "Respiratory: Sputum" ],
"percentage": [ 7.692308, 7.692308, 23.07692, 7.692308, 30.76923, 7.692308, 7.692308, 7.692308 ] 
},
"In...Out.Patient": {
 "In...Out.Patient": [ "Inpatient", "None Given", "Outpatient" ],
"percentage": [ 69.23077, 7.692308, 23.07692 ] 
} 
},
"Minocycline": {
 "State": {
 "State": [ "N/A" ],
"percentage": [      100 ] 
},
"Gender": {
 "Gender": [ "Female", "Male", "Not recorded" ],
"percentage": [ 44.44444, 33.33333, 22.22222 ] 
},
"Age.Group": {
 "Age.Group": [ "19 to 64 Years", "65 to 84 Years" ],
"percentage": [ 55.55556, 44.44444 ] 
},
"Speciality": {
 "Speciality": [ "Emergency Room", "Medicine General", "None Given", "Surgery General", "Surgery ICU" ],
"percentage": [ 22.22222, 22.22222, 33.33333, 11.11111, 11.11111 ] 
},
"Source": {
 "Source": [ "Bodily Fluids: Abscess / Pus", "CVS: Blood", "GU: Urine", "INT: Wound", "Respiratory: Bronchials", "Respiratory: Sputum" ],
"percentage": [ 11.11111, 22.22222, 22.22222, 11.11111, 11.11111, 22.22222 ] 
},
"In...Out.Patient": {
 "In...Out.Patient": [ "Inpatient", "None Given", "Outpatient" ],
"percentage": [ 44.44444, 33.33333, 22.22222 ] 
} 
},
"Piperacillin tazobactam": {
 "State": {
 "State": [ "N/A" ],
"percentage": [      100 ] 
},
"Gender": {
 "Gender": [ "Female", "Male", "Not recorded" ],
"percentage": [ 58.33333, 33.33333, 8.333333 ] 
},
"Age.Group": {
 "Age.Group": [ "19 to 64 Years", "65 to 84 Years" ],
"percentage": [ 58.33333, 41.66667 ] 
},
"Speciality": {
 "Speciality": [ "Emergency Room", "Medicine General", "Medicine ICU", "None Given", "Surgery General", "Surgery ICU" ],
"percentage": [       25, 33.33333, 16.66667, 8.333333, 8.333333, 8.333333 ] 
},
"Source": {
 "Source": [ "Bodily Fluids: Abdominal", "Bodily Fluids: Bile", "Bodily Fluids: Peritoneal", "CVS: Blood", "GI: Other", "GI: Pancreas", "GU: Urine", "INT: Wound", "Respiratory: Bronchials", "Respiratory: Sputum" ],
"percentage": [ 8.333333, 8.333333, 8.333333, 8.333333, 8.333333, 8.333333, 16.66667, 8.333333, 8.333333, 16.66667 ] 
},
"In...Out.Patient": {
 "In...Out.Patient": [ "Inpatient", "None Given", "Outpatient" ],
"percentage": [ 66.66667, 8.333333,       25 ] 
} 
} 
},
"percentage": [ 46.21849, 1.680672, 2.521008, 12.60504, 3.361345, 4.201681, 0.8403361, 10.92437, 7.563025, 10.08403 ],
"weight": 0.03363482,
"backgroundColor": [ "#1f78b4", "#b2df8a", "#ccebc5", "#fb9a99", "#d95f02", "#fdbf6f", "#b15928", "#8dd3c7", "#80b1d3", "#b3de69" ] 
},
"Resistant": {
 "Drug": {
 "Amikacin": {
 "State": {
 "State": [ "N/A" ],
"percentage": [      100 ] 
},
"Gender": {
 "Gender": [ "Female" ],
"percentage": [      100 ] 
},
"Age.Group": {
 "Age.Group": [ "19 to 64 Years" ],
"percentage": [      100 ] 
},
"Speciality": {
 "Speciality": [ "Medicine ICU" ],
"percentage": [      100 ] 
},
"Source": {
 "Source": [ "GI: Abscess" ],
"percentage": [      100 ] 
},
"In...Out.Patient": {
 "In...Out.Patient": [ "Inpatient" ],
"percentage": [      100 ] 
} 
},
"Amoxycillin clavulanate": {
 "State": {
 "State": [ "N/A" ],
"percentage": [      100 ] 
},
"Gender": {
 "Gender": [ "Female", "Male", "Not recorded" ],
"percentage": [ 46.66667, 46.66667, 6.666667 ] 
},
"Age.Group": {
 "Age.Group": [ "19 to 64 Years", "3 to 12 Years", "65 to 84 Years", "85 and Over" ],
"percentage": [       40, 4.444444, 42.22222, 13.33333 ] 
},
"Speciality": {
 "Speciality": [ "Emergency Room", "General Unspecified ICU", "Medicine General", "Medicine ICU", "None Given", "Other", "Surgery General", "Surgery ICU" ],
"percentage": [ 15.55556, 2.222222, 42.22222, 17.77778, 6.666667, 2.222222, 6.666667, 6.666667 ] 
},
"Source": {
 "Source": [ "Bodily Fluids: Abdominal", "Bodily Fluids: Bile", "Bodily Fluids: Peritoneal", "CVS: Blood", "GI: Abscess", "GI: Other", "GI: Pancreas", "GI: Small Colon", "GU: Prostate", "GU: Urine", "INT: Wound", "Respiratory: Bronchials", "Respiratory: Endotracheal aspirate", "Respiratory: Sputum" ],
"percentage": [ 2.222222, 2.222222, 4.444444, 17.77778, 4.444444, 4.444444, 2.222222, 2.222222, 2.222222, 22.22222, 4.444444, 4.444444, 4.444444, 22.22222 ] 
},
"In...Out.Patient": {
 "In...Out.Patient": [ "Inpatient", "None Given", "Outpatient" ],
"percentage": [ 75.55556, 8.888889, 15.55556 ] 
} 
},
"Ampicillin": {
 "State": {
 "State": [ "N/A" ],
"percentage": [      100 ] 
},
"Gender": {
 "Gender": [ "Female", "Male", "Not recorded" ],
"percentage": [ 47.17949, 44.61538, 8.205128 ] 
},
"Age.Group": {
 "Age.Group": [ "0 to 2 Years", "13 to 18 Years", "19 to 64 Years", "3 to 12 Years", "65 to 84 Years", "85 and Over" ],
"percentage": [ 2.564103, 0.5128205,  42.5641, 3.076923, 38.97436, 12.30769 ] 
},
"Speciality": {
 "Speciality": [ "Emergency Room", "General Unspecified ICU", "Medicine General", "Medicine ICU", "None Given", "Other", "Pediatric General", "Pediatric ICU", "Surgery General", "Surgery ICU" ],
"percentage": [ 16.41026, 1.025641, 41.53846, 13.33333, 5.128205, 2.051282, 1.538462, 1.025641, 11.79487, 6.153846 ] 
},
"Source": {
 "Source": [ "Bodily Fluids: Abdominal", "Bodily Fluids: Abscess / Pus", "Bodily Fluids: Bile", "Bodily Fluids: CSF", "Bodily Fluids: Exudate", "Bodily Fluids: Other", "Bodily Fluids: Peritoneal", "CVS: Blood", "GI: Abscess", "GI: Gall Bladder", "GI: Large Colon", "GI: Other", "GI: Pancreas", "GI: Rectum", "GI: Small Colon", "GU: Prostate", "GU: Urinary Bladder", "GU: Urine", "INT: Abscess", "INT: Decubitus", "INT: Other", "INT: Wound", "Respiratory", "Respiratory: Bronchials", "Respiratory: Bronchoalveolar lavage", "Respiratory: Endotracheal aspirate", "Respiratory: Other", "Respiratory: Sputum" ],
"percentage": [ 1.538462, 0.5128205, 1.025641, 0.5128205, 0.5128205, 0.5128205, 2.051282, 19.48718, 1.538462, 0.5128205, 1.025641, 3.076923, 1.025641, 0.5128205, 0.5128205, 0.5128205, 1.025641, 29.23077, 1.538462, 0.5128205, 1.538462, 4.615385, 0.5128205, 2.564103, 1.538462, 4.615385, 2.564103, 14.87179 ] 
},
"In...Out.Patient": {
 "In...Out.Patient": [ "Inpatient", "None Given", "Outpatient" ],
"percentage": [ 76.41026, 7.179487, 16.41026 ] 
} 
},
"Aztreonam": {
 "State": {
 "State": [ "N/A" ],
"percentage": [      100 ] 
},
"Gender": {
 "Gender": [ "Female", "Male" ],
"percentage": [ 52.38095, 47.61905 ] 
},
"Age.Group": {
 "Age.Group": [ "0 to 2 Years", "19 to 64 Years", "3 to 12 Years", "65 to 84 Years", "85 and Over" ],
"percentage": [  9.52381, 42.85714, 4.761905, 33.33333,  9.52381 ] 
},
"Speciality": {
 "Speciality": [ "Emergency Room", "Medicine General", "Medicine ICU", "Pediatric ICU", "Surgery General", "Surgery ICU" ],
"percentage": [ 14.28571, 47.61905, 14.28571, 4.761905, 14.28571, 4.761905 ] 
},
"Source": {
 "Source": [ "CVS: Blood", "GI: Other", "GU: Urine", "INT: Wound", "Respiratory: Endotracheal aspirate", "Respiratory: Sputum" ],
"percentage": [ 4.761905, 4.761905, 52.38095, 14.28571,  9.52381, 14.28571 ] 
},
"In...Out.Patient": {
 "In...Out.Patient": [ "Inpatient", "Outpatient" ],
"percentage": [ 85.71429, 14.28571 ] 
} 
},
"Cefepime": {
 "State": {
 "State": [ "N/A" ],
"percentage": [      100 ] 
},
"Gender": {
 "Gender": [ "Female", "Male", "Not recorded" ],
"percentage": [ 66.66667, 27.77778, 5.555556 ] 
},
"Age.Group": {
 "Age.Group": [ "0 to 2 Years", "19 to 64 Years", "3 to 12 Years", "65 to 84 Years", "85 and Over" ],
"percentage": [ 5.555556,       50, 2.777778, 27.77778, 13.88889 ] 
},
"Speciality": {
 "Speciality": [ "Emergency Room", "Medicine General", "Medicine ICU", "None Given", "Pediatric ICU", "Surgery General", "Surgery ICU" ],
"percentage": [ 22.22222, 38.88889, 16.66667, 5.555556, 2.777778, 8.333333, 5.555556 ] 
},
"Source": {
 "Source": [ "Bodily Fluids: Abdominal", "CVS: Blood", "GI: Abscess", "GI: Other", "GU: Urine", "INT: Wound", "Respiratory", "Respiratory: Bronchials", "Respiratory: Endotracheal aspirate", "Respiratory: Other", "Respiratory: Sputum" ],
"percentage": [ 2.777778, 13.88889, 2.777778, 5.555556, 38.88889, 11.11111, 2.777778, 2.777778, 2.777778, 2.777778, 13.88889 ] 
},
"In...Out.Patient": {
 "In...Out.Patient": [ "Inpatient", "None Given", "Outpatient" ],
"percentage": [ 72.22222, 5.555556, 22.22222 ] 
} 
},
"Ceftaroline": {
 "State": {
 "State": [ "N/A" ],
"percentage": [      100 ] 
},
"Gender": {
 "Gender": [ "Female", "Male" ],
"percentage": [       50,       50 ] 
},
"Age.Group": {
 "Age.Group": [ "0 to 2 Years", "19 to 64 Years", "3 to 12 Years", "65 to 84 Years", "85 and Over" ],
"percentage": [ 4.545455, 40.90909, 6.818182, 34.09091, 13.63636 ] 
},
"Speciality": {
 "Speciality": [ "Emergency Room", "Medicine General", "Medicine ICU", "Other", "Pediatric General", "Pediatric ICU", "Surgery General", "Surgery ICU" ],
"percentage": [ 11.36364, 43.18182, 20.45455, 2.272727, 2.272727, 2.272727, 13.63636, 4.545455 ] 
},
"Source": {
 "Source": [ "Bodily Fluids: Peritoneal", "CVS: Blood", "GI: Abscess", "GI: Other", "GI: Pancreas", "GU: Urine", "INT: Other", "INT: Wound", "Respiratory: Bronchials", "Respiratory: Endotracheal aspirate", "Respiratory: Sputum" ],
"percentage": [ 2.272727, 4.545455, 2.272727, 6.818182, 4.545455, 43.18182, 2.272727, 11.36364, 2.272727, 9.090909, 11.36364 ] 
},
"In...Out.Patient": {
 "In...Out.Patient": [ "Inpatient", "None Given", "Outpatient" ],
"percentage": [ 86.36364, 2.272727, 11.36364 ] 
} 
},
"Ceftazidime": {
 "State": {
 "State": [ "N/A" ],
"percentage": [      100 ] 
},
"Gender": {
 "Gender": [ "Female", "Male", "Not recorded" ],
"percentage": [ 54.83871, 38.70968, 6.451613 ] 
},
"Age.Group": {
 "Age.Group": [ "0 to 2 Years", "19 to 64 Years", "3 to 12 Years", "65 to 84 Years", "85 and Over" ],
"percentage": [ 6.451613,  48.3871, 3.225806, 32.25806, 9.677419 ] 
},
"Speciality": {
 "Speciality": [ "Emergency Room", "Medicine General", "Medicine ICU", "None Given", "Other", "Pediatric ICU", "Surgery General", "Surgery ICU" ],
"percentage": [ 16.12903, 41.93548, 12.90323, 6.451613, 3.225806, 3.225806, 9.677419, 6.451613 ] 
},
"Source": {
 "Source": [ "Bodily Fluids: Peritoneal", "CVS: Blood", "GI: Other", "GU: Urine", "INT: Wound", "Respiratory", "Respiratory: Endotracheal aspirate", "Respiratory: Other", "Respiratory: Sputum" ],
"percentage": [ 3.225806, 12.90323, 3.225806,  48.3871, 9.677419, 3.225806, 6.451613, 3.225806, 9.677419 ] 
},
"In...Out.Patient": {
 "In...Out.Patient": [ "Inpatient", "None Given", "Outpatient" ],
"percentage": [ 74.19355, 9.677419, 16.12903 ] 
} 
},
"Ceftriaxone": {
 "State": {
 "State": [ "N/A" ],
"percentage": [      100 ] 
},
"Gender": {
 "Gender": [ "Female", "Male", "Not recorded" ],
"percentage": [ 61.11111, 27.77778, 11.11111 ] 
},
"Age.Group": {
 "Age.Group": [ "19 to 64 Years", "65 to 84 Years", "85 and Over" ],
"percentage": [       50, 38.88889, 11.11111 ] 
},
"Speciality": {
 "Speciality": [ "Emergency Room", "Medicine General", "Medicine ICU", "None Given", "Surgery General", "Surgery ICU" ],
"percentage": [ 16.66667, 33.33333, 16.66667, 16.66667, 5.555556, 11.11111 ] 
},
"Source": {
 "Source": [ "Bodily Fluids: Abdominal", "Bodily Fluids: Peritoneal", "CVS: Blood", "GU: Urine", "INT: Wound", "Respiratory", "Respiratory: Bronchials", "Respiratory: Other", "Respiratory: Sputum" ],
"percentage": [ 5.555556, 5.555556, 33.33333, 27.77778, 5.555556, 5.555556, 5.555556, 5.555556, 5.555556 ] 
},
"In...Out.Patient": {
 "In...Out.Patient": [ "Inpatient", "None Given", "Outpatient" ],
"percentage": [ 66.66667, 16.66667, 16.66667 ] 
} 
},
"Doripenem": {
 "State": {
 "State": [ "N/A" ],
"percentage": [      100 ] 
},
"Gender": {
 "Gender": [ "Female" ],
"percentage": [      100 ] 
},
"Age.Group": {
 "Age.Group": [ "19 to 64 Years" ],
"percentage": [      100 ] 
},
"Speciality": {
 "Speciality": [ "Medicine General" ],
"percentage": [      100 ] 
},
"Source": {
 "Source": [ "GU: Urine" ],
"percentage": [      100 ] 
},
"In...Out.Patient": {
 "In...Out.Patient": [ "Inpatient" ],
"percentage": [      100 ] 
} 
},
"Levofloxacin": {
 "State": {
 "State": [ "N/A" ],
"percentage": [      100 ] 
},
"Gender": {
 "Gender": [ "Female", "Male", "Not recorded" ],
"percentage": [       50, 42.68293, 7.317073 ] 
},
"Age.Group": {
 "Age.Group": [ "0 to 2 Years", "19 to 64 Years", "3 to 12 Years", "65 to 84 Years", "85 and Over" ],
"percentage": [ 1.219512, 39.02439, 4.878049, 45.12195, 9.756098 ] 
},
"Speciality": {
 "Speciality": [ "Emergency Room", "Medicine General", "Medicine ICU", "None Given", "Other", "Pediatric General", "Surgery General", "Surgery ICU" ],
"percentage": [ 20.73171, 47.56098, 10.97561, 1.219512, 1.219512, 1.219512, 10.97561, 6.097561 ] 
},
"Source": {
 "Source": [ "Bodily Fluids: Peritoneal", "CVS: Blood", "GI: Abscess", "GI: Large Colon", "GI: Other", "GI: Pancreas", "GI: Rectum", "GI: Small Colon", "GU: Other", "GU: Urine", "INT: Abscess", "INT: Decubitus", "INT: Other", "INT: Wound", "Respiratory", "Respiratory: Bronchials", "Respiratory: Endotracheal aspirate", "Respiratory: Other", "Respiratory: Sputum" ],
"percentage": [ 2.439024, 21.95122, 3.658537, 1.219512, 2.439024, 1.219512, 1.219512, 2.439024, 1.219512, 39.02439, 2.439024, 1.219512, 1.219512, 2.439024, 1.219512, 2.439024, 3.658537, 1.219512, 7.317073 ] 
},
"In...Out.Patient": {
 "In...Out.Patient": [ "Inpatient", "None Given", "Outpatient" ],
"percentage": [ 76.82927, 2.439024, 20.73171 ] 
} 
},
"Meropenem": {
 "State": {
 "State": [ "N/A" ],
"percentage": [      100 ] 
},
"Gender": {
 "Gender": [ "Female" ],
"percentage": [      100 ] 
},
"Age.Group": {
 "Age.Group": [ "19 to 64 Years" ],
"percentage": [      100 ] 
},
"Speciality": {
 "Speciality": [ "Medicine General" ],
"percentage": [      100 ] 
},
"Source": {
 "Source": [ "GU: Urine" ],
"percentage": [      100 ] 
},
"In...Out.Patient": {
 "In...Out.Patient": [ "Inpatient" ],
"percentage": [      100 ] 
} 
},
"Minocycline": {
 "State": {
 "State": [ "N/A" ],
"percentage": [      100 ] 
},
"Gender": {
 "Gender": [ "Female", "Male", "Not recorded" ],
"percentage": [ 33.33333, 33.33333, 33.33333 ] 
},
"Age.Group": {
 "Age.Group": [ "19 to 64 Years", "3 to 12 Years", "65 to 84 Years" ],
"percentage": [ 44.44444, 11.11111, 44.44444 ] 
},
"Speciality": {
 "Speciality": [ "Emergency Room", "Medicine General", "Medicine ICU", "None Given", "Surgery General", "Surgery ICU" ],
"percentage": [ 22.22222, 11.11111, 22.22222, 11.11111, 22.22222, 11.11111 ] 
},
"Source": {
 "Source": [ "Bodily Fluids: Exudate", "CVS: Blood", "GU: Urine", "Respiratory: Other" ],
"percentage": [ 11.11111, 55.55556, 22.22222, 11.11111 ] 
},
"In...Out.Patient": {
 "In...Out.Patient": [ "Inpatient", "None Given", "Outpatient" ],
"percentage": [ 66.66667, 11.11111, 22.22222 ] 
} 
},
"Piperacillin tazobactam": {
 "State": {
 "State": [ "N/A" ],
"percentage": [      100 ] 
},
"Gender": {
 "Gender": [ "Female", "Male", "Not recorded" ],
"percentage": [       40,       55,        5 ] 
},
"Age.Group": {
 "Age.Group": [ "19 to 64 Years", "3 to 12 Years", "65 to 84 Years", "85 and Over" ],
"percentage": [       35,        5,       40,       20 ] 
},
"Speciality": {
 "Speciality": [ "Emergency Room", "Medicine General", "Medicine ICU", "None Given" ],
"percentage": [       20,       50,       25,        5 ] 
},
"Source": {
 "Source": [ "Bodily Fluids: Peritoneal", "CVS: Blood", "GI: Abscess", "GI: Other", "GU: Urine", "Respiratory: Bronchials", "Respiratory: Endotracheal aspirate", "Respiratory: Sputum" ],
"percentage": [        5,       20,       10,        5,       15,        5,        5,       35 ] 
},
"In...Out.Patient": {
 "In...Out.Patient": [ "Inpatient", "None Given", "Outpatient" ],
"percentage": [       75,        5,       20 ] 
} 
} 
},
"percentage": [ 0.1980198, 8.910891, 38.61386, 4.158416, 7.128713, 8.712871, 6.138614, 3.564356, 0.1980198, 16.23762, 0.3960396, 1.782178, 3.960396 ],
"weight": 0.142736,
"backgroundColor": [ "#a6cee3", "#1f78b4", "#b2df8a", "#ccebc5", "#fb9a99", "#d95f02", "#fdbf6f", "#ff7f00", "#e41a1c", "#8dd3c7", "#bebada", "#80b1d3", "#b3de69" ] 
} 
}
