{
 "Susceptible": {
 "Drug": {
 "Amikacin": {
 "State": {
 "State": [ "N/A" ],
"percentage": [      100 ] 
},
"Gender": {
 "Gender": [ "Female", "Male" ],
"percentage": [ 48.64865, 51.35135 ] 
},
"Age.Group": {
 "Age.Group": [ "0 to 2 Years", "19 to 64 Years", "3 to 12 Years", "65 to 84 Years", "85 and Over" ],
"percentage": [ 2.702703, 18.91892, 5.405405, 48.64865, 24.32432 ] 
},
"Speciality": {
 "Speciality": [ "Clinic / Office", "Emergency Room", "Medicine General", "Pediatric General", "Pediatric ICU", "Surgery General", "Surgery ICU" ],
"percentage": [ 13.51351, 10.81081, 37.83784, 5.405405, 2.702703, 27.02703, 2.702703 ] 
},
"Source": {
 "Source": [ "CVS: Blood", "GU: Urethra", "GU: Urinary Bladder", "GU: Urine", "HEENT: Eyes", "INT: Carbuncle", "Integumentary (INT)", "INT: Other", "Skeletal: Bone" ],
"percentage": [ 16.21622, 5.405405, 10.81081, 54.05405, 2.702703, 2.702703, 2.702703, 2.702703, 2.702703 ] 
},
"In...Out.Patient": {
 "In...Out.Patient": [ "Inpatient", "Outpatient" ],
"percentage": [ 75.67568, 24.32432 ] 
} 
},
"Amoxycillin clavulanate": {
 "State": {
 "State": [ "N/A" ],
"percentage": [      100 ] 
},
"Gender": {
 "Gender": [ "Female", "Male" ],
"percentage": [ 51.42857, 48.57143 ] 
},
"Age.Group": {
 "Age.Group": [ "0 to 2 Years", "19 to 64 Years", "3 to 12 Years", "65 to 84 Years", "85 and Over" ],
"percentage": [ 2.857143,       20, 5.714286, 45.71429, 25.71429 ] 
},
"Speciality": {
 "Speciality": [ "Clinic / Office", "Emergency Room", "Medicine General", "Pediatric General", "Pediatric ICU", "Surgery General", "Surgery ICU" ],
"percentage": [ 14.28571, 5.714286,       40, 5.714286, 2.857143, 28.57143, 2.857143 ] 
},
"Source": {
 "Source": [ "CVS: Blood", "GU: Urethra", "GU: Urinary Bladder", "GU: Urine", "HEENT: Eyes", "INT: Carbuncle", "Integumentary (INT)", "INT: Other", "Skeletal: Bone" ],
"percentage": [ 17.14286, 5.714286, 11.42857, 51.42857, 2.857143, 2.857143, 2.857143, 2.857143, 2.857143 ] 
},
"In...Out.Patient": {
 "In...Out.Patient": [ "Inpatient", "Outpatient" ],
"percentage": [       80,       20 ] 
} 
},
"Ampicillin": {
 "State": {
 "State": [ "N/A" ],
"percentage": [      100 ] 
},
"Gender": {
 "Gender": [ "Female" ],
"percentage": [      100 ] 
},
"Age.Group": {
 "Age.Group": [ "85 and Over" ],
"percentage": [      100 ] 
},
"Speciality": {
 "Speciality": [ "Surgery General" ],
"percentage": [      100 ] 
},
"Source": {
 "Source": [ "GU: Urine" ],
"percentage": [      100 ] 
},
"In...Out.Patient": {
 "In...Out.Patient": [ "Inpatient" ],
"percentage": [      100 ] 
} 
},
"Aztreonam": {
 "State": {
 "State": [ "N/A" ],
"percentage": [      100 ] 
},
"Gender": {
 "Gender": [ "Female", "Male" ],
"percentage": [ 38.46154, 61.53846 ] 
},
"Age.Group": {
 "Age.Group": [ "19 to 64 Years", "3 to 12 Years", "65 to 84 Years", "85 and Over" ],
"percentage": [ 15.38462, 7.692308, 46.15385, 30.76923 ] 
},
"Speciality": {
 "Speciality": [ "Emergency Room", "Medicine General", "Pediatric General", "Surgery General" ],
"percentage": [ 15.38462, 53.84615, 7.692308, 23.07692 ] 
},
"Source": {
 "Source": [ "GU: Urine", "INT: Carbuncle", "INT: Other" ],
"percentage": [ 84.61538, 7.692308, 7.692308 ] 
},
"In...Out.Patient": {
 "In...Out.Patient": [ "Inpatient", "Outpatient" ],
"percentage": [ 84.61538, 15.38462 ] 
} 
},
"Cefepime": {
 "State": {
 "State": [ "N/A" ],
"percentage": [      100 ] 
},
"Gender": {
 "Gender": [ "Female", "Male" ],
"percentage": [ 48.64865, 51.35135 ] 
},
"Age.Group": {
 "Age.Group": [ "0 to 2 Years", "19 to 64 Years", "3 to 12 Years", "65 to 84 Years", "85 and Over" ],
"percentage": [ 2.702703, 18.91892, 5.405405, 48.64865, 24.32432 ] 
},
"Speciality": {
 "Speciality": [ "Clinic / Office", "Emergency Room", "Medicine General", "Pediatric General", "Pediatric ICU", "Surgery General", "Surgery ICU" ],
"percentage": [ 13.51351, 10.81081, 37.83784, 5.405405, 2.702703, 27.02703, 2.702703 ] 
},
"Source": {
 "Source": [ "CVS: Blood", "GU: Urethra", "GU: Urinary Bladder", "GU: Urine", "HEENT: Eyes", "INT: Carbuncle", "Integumentary (INT)", "INT: Other", "Skeletal: Bone" ],
"percentage": [ 16.21622, 5.405405, 10.81081, 54.05405, 2.702703, 2.702703, 2.702703, 2.702703, 2.702703 ] 
},
"In...Out.Patient": {
 "In...Out.Patient": [ "Inpatient", "Outpatient" ],
"percentage": [ 75.67568, 24.32432 ] 
} 
},
"Ceftaroline": {
 "State": {
 "State": [ "N/A" ],
"percentage": [      100 ] 
},
"Gender": {
 "Gender": [ "Female", "Male" ],
"percentage": [ 38.46154, 61.53846 ] 
},
"Age.Group": {
 "Age.Group": [ "19 to 64 Years", "3 to 12 Years", "65 to 84 Years", "85 and Over" ],
"percentage": [ 15.38462, 7.692308, 46.15385, 30.76923 ] 
},
"Speciality": {
 "Speciality": [ "Emergency Room", "Medicine General", "Pediatric General", "Surgery General" ],
"percentage": [ 15.38462, 53.84615, 7.692308, 23.07692 ] 
},
"Source": {
 "Source": [ "GU: Urine", "INT: Carbuncle", "INT: Other" ],
"percentage": [ 84.61538, 7.692308, 7.692308 ] 
},
"In...Out.Patient": {
 "In...Out.Patient": [ "Inpatient", "Outpatient" ],
"percentage": [ 84.61538, 15.38462 ] 
} 
},
"Ceftazidime": {
 "State": {
 "State": [ "N/A" ],
"percentage": [      100 ] 
},
"Gender": {
 "Gender": [ "Female", "Male" ],
"percentage": [ 48.64865, 51.35135 ] 
},
"Age.Group": {
 "Age.Group": [ "0 to 2 Years", "19 to 64 Years", "3 to 12 Years", "65 to 84 Years", "85 and Over" ],
"percentage": [ 2.702703, 18.91892, 5.405405, 48.64865, 24.32432 ] 
},
"Speciality": {
 "Speciality": [ "Clinic / Office", "Emergency Room", "Medicine General", "Pediatric General", "Pediatric ICU", "Surgery General", "Surgery ICU" ],
"percentage": [ 13.51351, 10.81081, 37.83784, 5.405405, 2.702703, 27.02703, 2.702703 ] 
},
"Source": {
 "Source": [ "CVS: Blood", "GU: Urethra", "GU: Urinary Bladder", "GU: Urine", "HEENT: Eyes", "INT: Carbuncle", "Integumentary (INT)", "INT: Other", "Skeletal: Bone" ],
"percentage": [ 16.21622, 5.405405, 10.81081, 54.05405, 2.702703, 2.702703, 2.702703, 2.702703, 2.702703 ] 
},
"In...Out.Patient": {
 "In...Out.Patient": [ "Inpatient", "Outpatient" ],
"percentage": [ 75.67568, 24.32432 ] 
} 
},
"Ceftazidime avibactam": {
 "State": {
 "State": [ "N/A" ],
"percentage": [      100 ] 
},
"Gender": {
 "Gender": [ "Female", "Male" ],
"percentage": [ 38.46154, 61.53846 ] 
},
"Age.Group": {
 "Age.Group": [ "19 to 64 Years", "3 to 12 Years", "65 to 84 Years", "85 and Over" ],
"percentage": [ 15.38462, 7.692308, 46.15385, 30.76923 ] 
},
"Speciality": {
 "Speciality": [ "Emergency Room", "Medicine General", "Pediatric General", "Surgery General" ],
"percentage": [ 15.38462, 53.84615, 7.692308, 23.07692 ] 
},
"Source": {
 "Source": [ "GU: Urine", "INT: Carbuncle", "INT: Other" ],
"percentage": [ 84.61538, 7.692308, 7.692308 ] 
},
"In...Out.Patient": {
 "In...Out.Patient": [ "Inpatient", "Outpatient" ],
"percentage": [ 84.61538, 15.38462 ] 
} 
},
"Ceftriaxone": {
 "State": {
 "State": [ "N/A" ],
"percentage": [      100 ] 
},
"Gender": {
 "Gender": [ "Female", "Male" ],
"percentage": [ 54.16667, 45.83333 ] 
},
"Age.Group": {
 "Age.Group": [ "0 to 2 Years", "19 to 64 Years", "3 to 12 Years", "65 to 84 Years", "85 and Over" ],
"percentage": [ 4.166667, 20.83333, 4.166667,       50, 20.83333 ] 
},
"Speciality": {
 "Speciality": [ "Clinic / Office", "Emergency Room", "Medicine General", "Pediatric General", "Pediatric ICU", "Surgery General", "Surgery ICU" ],
"percentage": [ 20.83333, 8.333333, 29.16667, 4.166667, 4.166667, 29.16667, 4.166667 ] 
},
"Source": {
 "Source": [ "CVS: Blood", "GU: Urethra", "GU: Urinary Bladder", "GU: Urine", "HEENT: Eyes", "Integumentary (INT)", "Skeletal: Bone" ],
"percentage": [       25, 8.333333, 16.66667,     37.5, 4.166667, 4.166667, 4.166667 ] 
},
"In...Out.Patient": {
 "In...Out.Patient": [ "Inpatient", "Outpatient" ],
"percentage": [ 70.83333, 29.16667 ] 
} 
},
"Doripenem": {
 "State": {
 "State": [ "N/A" ],
"percentage": [      100 ] 
},
"Gender": {
 "Gender": [ "Female", "Male" ],
"percentage": [ 38.46154, 61.53846 ] 
},
"Age.Group": {
 "Age.Group": [ "19 to 64 Years", "3 to 12 Years", "65 to 84 Years", "85 and Over" ],
"percentage": [ 15.38462, 7.692308, 46.15385, 30.76923 ] 
},
"Speciality": {
 "Speciality": [ "Emergency Room", "Medicine General", "Pediatric General", "Surgery General" ],
"percentage": [ 15.38462, 53.84615, 7.692308, 23.07692 ] 
},
"Source": {
 "Source": [ "GU: Urine", "INT: Carbuncle", "INT: Other" ],
"percentage": [ 84.61538, 7.692308, 7.692308 ] 
},
"In...Out.Patient": {
 "In...Out.Patient": [ "Inpatient", "Outpatient" ],
"percentage": [ 84.61538, 15.38462 ] 
} 
},
"Imipenem": {
 "State": {
 "State": [ "N/A" ],
"percentage": [      100 ] 
},
"Gender": {
 "Gender": [ "Female", "Male" ],
"percentage": [ 38.46154, 61.53846 ] 
},
"Age.Group": {
 "Age.Group": [ "19 to 64 Years", "3 to 12 Years", "65 to 84 Years", "85 and Over" ],
"percentage": [ 15.38462, 7.692308, 46.15385, 30.76923 ] 
},
"Speciality": {
 "Speciality": [ "Emergency Room", "Medicine General", "Pediatric General", "Surgery General" ],
"percentage": [ 15.38462, 53.84615, 7.692308, 23.07692 ] 
},
"Source": {
 "Source": [ "GU: Urine", "INT: Carbuncle", "INT: Other" ],
"percentage": [ 84.61538, 7.692308, 7.692308 ] 
},
"In...Out.Patient": {
 "In...Out.Patient": [ "Inpatient", "Outpatient" ],
"percentage": [ 84.61538, 15.38462 ] 
} 
},
"Levofloxacin": {
 "State": {
 "State": [ "N/A" ],
"percentage": [      100 ] 
},
"Gender": {
 "Gender": [ "Female", "Male" ],
"percentage": [ 48.64865, 51.35135 ] 
},
"Age.Group": {
 "Age.Group": [ "0 to 2 Years", "19 to 64 Years", "3 to 12 Years", "65 to 84 Years", "85 and Over" ],
"percentage": [ 2.702703, 18.91892, 5.405405, 48.64865, 24.32432 ] 
},
"Speciality": {
 "Speciality": [ "Clinic / Office", "Emergency Room", "Medicine General", "Pediatric General", "Pediatric ICU", "Surgery General", "Surgery ICU" ],
"percentage": [ 13.51351, 10.81081, 37.83784, 5.405405, 2.702703, 27.02703, 2.702703 ] 
},
"Source": {
 "Source": [ "CVS: Blood", "GU: Urethra", "GU: Urinary Bladder", "GU: Urine", "HEENT: Eyes", "INT: Carbuncle", "Integumentary (INT)", "INT: Other", "Skeletal: Bone" ],
"percentage": [ 16.21622, 5.405405, 10.81081, 54.05405, 2.702703, 2.702703, 2.702703, 2.702703, 2.702703 ] 
},
"In...Out.Patient": {
 "In...Out.Patient": [ "Inpatient", "Outpatient" ],
"percentage": [ 75.67568, 24.32432 ] 
} 
},
"Meropenem": {
 "State": {
 "State": [ "N/A" ],
"percentage": [      100 ] 
},
"Gender": {
 "Gender": [ "Female", "Male" ],
"percentage": [ 48.64865, 51.35135 ] 
},
"Age.Group": {
 "Age.Group": [ "0 to 2 Years", "19 to 64 Years", "3 to 12 Years", "65 to 84 Years", "85 and Over" ],
"percentage": [ 2.702703, 18.91892, 5.405405, 48.64865, 24.32432 ] 
},
"Speciality": {
 "Speciality": [ "Clinic / Office", "Emergency Room", "Medicine General", "Pediatric General", "Pediatric ICU", "Surgery General", "Surgery ICU" ],
"percentage": [ 13.51351, 10.81081, 37.83784, 5.405405, 2.702703, 27.02703, 2.702703 ] 
},
"Source": {
 "Source": [ "CVS: Blood", "GU: Urethra", "GU: Urinary Bladder", "GU: Urine", "HEENT: Eyes", "INT: Carbuncle", "Integumentary (INT)", "INT: Other", "Skeletal: Bone" ],
"percentage": [ 16.21622, 5.405405, 10.81081, 54.05405, 2.702703, 2.702703, 2.702703, 2.702703, 2.702703 ] 
},
"In...Out.Patient": {
 "In...Out.Patient": [ "Inpatient", "Outpatient" ],
"percentage": [ 75.67568, 24.32432 ] 
} 
},
"Minocycline": {
 "State": {
 "State": [ "N/A" ],
"percentage": [      100 ] 
},
"Gender": {
 "Gender": [ "Female", "Male" ],
"percentage": [ 54.16667, 45.83333 ] 
},
"Age.Group": {
 "Age.Group": [ "0 to 2 Years", "19 to 64 Years", "3 to 12 Years", "65 to 84 Years", "85 and Over" ],
"percentage": [ 4.166667, 20.83333, 4.166667,       50, 20.83333 ] 
},
"Speciality": {
 "Speciality": [ "Clinic / Office", "Emergency Room", "Medicine General", "Pediatric General", "Pediatric ICU", "Surgery General", "Surgery ICU" ],
"percentage": [ 20.83333, 8.333333, 29.16667, 4.166667, 4.166667, 29.16667, 4.166667 ] 
},
"Source": {
 "Source": [ "CVS: Blood", "GU: Urethra", "GU: Urinary Bladder", "GU: Urine", "HEENT: Eyes", "Integumentary (INT)", "Skeletal: Bone" ],
"percentage": [       25, 8.333333, 16.66667,     37.5, 4.166667, 4.166667, 4.166667 ] 
},
"In...Out.Patient": {
 "In...Out.Patient": [ "Inpatient", "Outpatient" ],
"percentage": [ 70.83333, 29.16667 ] 
} 
},
"Piperacillin tazobactam": {
 "State": {
 "State": [ "N/A" ],
"percentage": [      100 ] 
},
"Gender": {
 "Gender": [ "Female", "Male" ],
"percentage": [ 48.64865, 51.35135 ] 
},
"Age.Group": {
 "Age.Group": [ "0 to 2 Years", "19 to 64 Years", "3 to 12 Years", "65 to 84 Years", "85 and Over" ],
"percentage": [ 2.702703, 18.91892, 5.405405, 48.64865, 24.32432 ] 
},
"Speciality": {
 "Speciality": [ "Clinic / Office", "Emergency Room", "Medicine General", "Pediatric General", "Pediatric ICU", "Surgery General", "Surgery ICU" ],
"percentage": [ 13.51351, 10.81081, 37.83784, 5.405405, 2.702703, 27.02703, 2.702703 ] 
},
"Source": {
 "Source": [ "CVS: Blood", "GU: Urethra", "GU: Urinary Bladder", "GU: Urine", "HEENT: Eyes", "INT: Carbuncle", "Integumentary (INT)", "INT: Other", "Skeletal: Bone" ],
"percentage": [ 16.21622, 5.405405, 10.81081, 54.05405, 2.702703, 2.702703, 2.702703, 2.702703, 2.702703 ] 
},
"In...Out.Patient": {
 "In...Out.Patient": [ "Inpatient", "Outpatient" ],
"percentage": [ 75.67568, 24.32432 ] 
} 
},
"Tigecycline": {
 "State": {
 "State": [ "N/A" ],
"percentage": [      100 ] 
},
"Gender": {
 "Gender": [ "Female", "Male" ],
"percentage": [ 48.64865, 51.35135 ] 
},
"Age.Group": {
 "Age.Group": [ "0 to 2 Years", "19 to 64 Years", "3 to 12 Years", "65 to 84 Years", "85 and Over" ],
"percentage": [ 2.702703, 18.91892, 5.405405, 48.64865, 24.32432 ] 
},
"Speciality": {
 "Speciality": [ "Clinic / Office", "Emergency Room", "Medicine General", "Pediatric General", "Pediatric ICU", "Surgery General", "Surgery ICU" ],
"percentage": [ 13.51351, 10.81081, 37.83784, 5.405405, 2.702703, 27.02703, 2.702703 ] 
},
"Source": {
 "Source": [ "CVS: Blood", "GU: Urethra", "GU: Urinary Bladder", "GU: Urine", "HEENT: Eyes", "INT: Carbuncle", "Integumentary (INT)", "INT: Other", "Skeletal: Bone" ],
"percentage": [ 16.21622, 5.405405, 10.81081, 54.05405, 2.702703, 2.702703, 2.702703, 2.702703, 2.702703 ] 
},
"In...Out.Patient": {
 "In...Out.Patient": [ "Inpatient", "Outpatient" ],
"percentage": [ 75.67568, 24.32432 ] 
} 
} 
},
"percentage": [ 9.068627, 8.578431, 0.245098, 3.186275, 9.068627, 3.186275, 9.068627, 3.186275, 5.882353, 3.186275, 3.186275, 9.068627, 9.068627, 5.882353, 9.068627, 9.068627 ],
"weight": 0.9147982,
"backgroundColor": [ "#a6cee3", "#1f78b4", "#b2df8a", "#ccebc5", "#fb9a99", "#d95f02", "#fdbf6f", "#e7298a", "#ff7f00", "#e41a1c", "#b15928", "#8dd3c7", "#bebada", "#80b1d3", "#b3de69", "#fccde5" ] 
},
"Intermediate": {
 "Drug": {
 "Amoxycillin clavulanate": {
 "State": {
 "State": [ "N/A" ],
"percentage": [      100 ] 
},
"Gender": {
 "Gender": [ "Male" ],
"percentage": [      100 ] 
},
"Age.Group": {
 "Age.Group": [ "65 to 84 Years" ],
"percentage": [      100 ] 
},
"Speciality": {
 "Speciality": [ "Emergency Room" ],
"percentage": [      100 ] 
},
"Source": {
 "Source": [ "GU: Urine" ],
"percentage": [      100 ] 
},
"In...Out.Patient": {
 "In...Out.Patient": [ "Outpatient" ],
"percentage": [      100 ] 
} 
} 
},
"percentage":      100,
"weight": 0.004484305,
"backgroundColor": "#1f78b4" 
},
"Resistant": {
 "Drug": {
 "Ampicillin": {
 "State": {
 "State": [ "N/A" ],
"percentage": [      100 ] 
},
"Gender": {
 "Gender": [ "Female", "Male" ],
"percentage": [ 47.22222, 52.77778 ] 
},
"Age.Group": {
 "Age.Group": [ "0 to 2 Years", "19 to 64 Years", "3 to 12 Years", "65 to 84 Years", "85 and Over" ],
"percentage": [ 2.777778, 19.44444, 5.555556,       50, 22.22222 ] 
},
"Speciality": {
 "Speciality": [ "Clinic / Office", "Emergency Room", "Medicine General", "Pediatric General", "Pediatric ICU", "Surgery General", "Surgery ICU" ],
"percentage": [ 13.88889, 11.11111, 38.88889, 5.555556, 2.777778,       25, 2.777778 ] 
},
"Source": {
 "Source": [ "CVS: Blood", "GU: Urethra", "GU: Urinary Bladder", "GU: Urine", "HEENT: Eyes", "INT: Carbuncle", "Integumentary (INT)", "INT: Other", "Skeletal: Bone" ],
"percentage": [ 16.66667, 5.555556, 11.11111, 52.77778, 2.777778, 2.777778, 2.777778, 2.777778, 2.777778 ] 
},
"In...Out.Patient": {
 "In...Out.Patient": [ "Inpatient", "Outpatient" ],
"percentage": [       75,       25 ] 
} 
} 
},
"percentage":      100,
"weight": 0.08071749,
"backgroundColor": "#b2df8a" 
} 
}
