{
 "Susceptible": {
 "Drug": {
 "Cefoxitin": {
 "State": {
 "State": [ "N/A" ],
"percentage": [      100 ] 
},
"Gender": {
 "Gender": [ "Female", "Male", "Not recorded" ],
"percentage": [ 54.16667, 41.66667, 4.166667 ] 
},
"Age.Group": {
 "Age.Group": [ "0 to 2 Years", "19 to 64 Years", "3 to 12 Years", "65 to 84 Years", "Unknown" ],
"percentage": [     12.5, 45.83333, 4.166667, 20.83333, 16.66667 ] 
},
"Speciality": {
 "Speciality": [ "Clinic / Office", "Medicine General", "None Given", "Surgery General" ],
"percentage": [ 45.83333, 33.33333,     12.5, 8.333333 ] 
},
"Source": {
 "Source": [ "Bodily Fluids", "Bodily Fluids: Abscess / Pus", "Bodily Fluids: Ulcer", "INT: Wound", "Reproductive: Uterus", "Respiratory: Other", "Respiratory: Sinuses" ],
"percentage": [ 8.333333, 33.33333, 8.333333,     37.5, 4.166667, 4.166667, 4.166667 ] 
},
"In...Out.Patient": {
 "In...Out.Patient": [ "Inpatient", "None Given", "Outpatient" ],
"percentage": [ 41.66667,     12.5, 45.83333 ] 
} 
},
"Clindamycin": {
 "State": {
 "State": [ "N/A" ],
"percentage": [      100 ] 
},
"Gender": {
 "Gender": [ "Female", "Male", "Not recorded" ],
"percentage": [ 56.52174, 39.13043, 4.347826 ] 
},
"Age.Group": {
 "Age.Group": [ "0 to 2 Years", "19 to 64 Years", "3 to 12 Years", "65 to 84 Years", "Unknown" ],
"percentage": [ 13.04348, 47.82609, 4.347826,  17.3913,  17.3913 ] 
},
"Speciality": {
 "Speciality": [ "Clinic / Office", "Medicine General", "None Given", "Surgery General" ],
"percentage": [ 43.47826, 34.78261, 13.04348, 8.695652 ] 
},
"Source": {
 "Source": [ "Bodily Fluids", "Bodily Fluids: Abscess / Pus", "Bodily Fluids: Ulcer", "INT: Wound", "Reproductive: Uterus", "Respiratory: Other", "Respiratory: Sinuses" ],
"percentage": [ 8.695652, 34.78261, 8.695652, 34.78261, 4.347826, 4.347826, 4.347826 ] 
},
"In...Out.Patient": {
 "In...Out.Patient": [ "Inpatient", "None Given", "Outpatient" ],
"percentage": [ 43.47826, 13.04348, 43.47826 ] 
} 
},
"Meropenem": {
 "State": {
 "State": [ "N/A" ],
"percentage": [      100 ] 
},
"Gender": {
 "Gender": [ "Female", "Male", "Not recorded" ],
"percentage": [ 54.16667, 41.66667, 4.166667 ] 
},
"Age.Group": {
 "Age.Group": [ "0 to 2 Years", "19 to 64 Years", "3 to 12 Years", "65 to 84 Years", "Unknown" ],
"percentage": [     12.5, 45.83333, 4.166667, 20.83333, 16.66667 ] 
},
"Speciality": {
 "Speciality": [ "Clinic / Office", "Medicine General", "None Given", "Surgery General" ],
"percentage": [ 45.83333, 33.33333,     12.5, 8.333333 ] 
},
"Source": {
 "Source": [ "Bodily Fluids", "Bodily Fluids: Abscess / Pus", "Bodily Fluids: Ulcer", "INT: Wound", "Reproductive: Uterus", "Respiratory: Other", "Respiratory: Sinuses" ],
"percentage": [ 8.333333, 33.33333, 8.333333,     37.5, 4.166667, 4.166667, 4.166667 ] 
},
"In...Out.Patient": {
 "In...Out.Patient": [ "Inpatient", "None Given", "Outpatient" ],
"percentage": [ 41.66667,     12.5, 45.83333 ] 
} 
},
"Metronidazole": {
 "State": {
 "State": [ "N/A" ],
"percentage": [      100 ] 
},
"Gender": {
 "Gender": [ "Female", "Male", "Not recorded" ],
"percentage": [ 54.16667, 41.66667, 4.166667 ] 
},
"Age.Group": {
 "Age.Group": [ "0 to 2 Years", "19 to 64 Years", "3 to 12 Years", "65 to 84 Years", "Unknown" ],
"percentage": [     12.5, 45.83333, 4.166667, 20.83333, 16.66667 ] 
},
"Speciality": {
 "Speciality": [ "Clinic / Office", "Medicine General", "None Given", "Surgery General" ],
"percentage": [ 45.83333, 33.33333,     12.5, 8.333333 ] 
},
"Source": {
 "Source": [ "Bodily Fluids", "Bodily Fluids: Abscess / Pus", "Bodily Fluids: Ulcer", "INT: Wound", "Reproductive: Uterus", "Respiratory: Other", "Respiratory: Sinuses" ],
"percentage": [ 8.333333, 33.33333, 8.333333,     37.5, 4.166667, 4.166667, 4.166667 ] 
},
"In...Out.Patient": {
 "In...Out.Patient": [ "Inpatient", "None Given", "Outpatient" ],
"percentage": [ 41.66667,     12.5, 45.83333 ] 
} 
},
"Piperacillin tazobactam": {
 "State": {
 "State": [ "N/A" ],
"percentage": [      100 ] 
},
"Gender": {
 "Gender": [ "Female", "Male", "Not recorded" ],
"percentage": [ 54.16667, 41.66667, 4.166667 ] 
},
"Age.Group": {
 "Age.Group": [ "0 to 2 Years", "19 to 64 Years", "3 to 12 Years", "65 to 84 Years", "Unknown" ],
"percentage": [     12.5, 45.83333, 4.166667, 20.83333, 16.66667 ] 
},
"Speciality": {
 "Speciality": [ "Clinic / Office", "Medicine General", "None Given", "Surgery General" ],
"percentage": [ 45.83333, 33.33333,     12.5, 8.333333 ] 
},
"Source": {
 "Source": [ "Bodily Fluids", "Bodily Fluids: Abscess / Pus", "Bodily Fluids: Ulcer", "INT: Wound", "Reproductive: Uterus", "Respiratory: Other", "Respiratory: Sinuses" ],
"percentage": [ 8.333333, 33.33333, 8.333333,     37.5, 4.166667, 4.166667, 4.166667 ] 
},
"In...Out.Patient": {
 "In...Out.Patient": [ "Inpatient", "None Given", "Outpatient" ],
"percentage": [ 41.66667,     12.5, 45.83333 ] 
} 
},
"Tigecycline": {
 "State": {
 "State": [ "N/A" ],
"percentage": [      100 ] 
},
"Gender": {
 "Gender": [ "Female", "Male", "Not recorded" ],
"percentage": [ 54.16667, 41.66667, 4.166667 ] 
},
"Age.Group": {
 "Age.Group": [ "0 to 2 Years", "19 to 64 Years", "3 to 12 Years", "65 to 84 Years", "Unknown" ],
"percentage": [     12.5, 45.83333, 4.166667, 20.83333, 16.66667 ] 
},
"Speciality": {
 "Speciality": [ "Clinic / Office", "Medicine General", "None Given", "Surgery General" ],
"percentage": [ 45.83333, 33.33333,     12.5, 8.333333 ] 
},
"Source": {
 "Source": [ "Bodily Fluids", "Bodily Fluids: Abscess / Pus", "Bodily Fluids: Ulcer", "INT: Wound", "Reproductive: Uterus", "Respiratory: Other", "Respiratory: Sinuses" ],
"percentage": [ 8.333333, 33.33333, 8.333333,     37.5, 4.166667, 4.166667, 4.166667 ] 
},
"In...Out.Patient": {
 "In...Out.Patient": [ "Inpatient", "None Given", "Outpatient" ],
"percentage": [ 41.66667,     12.5, 45.83333 ] 
} 
} 
},
"percentage": [ 16.78322, 16.08392, 16.78322, 16.78322, 16.78322, 16.78322 ],
"weight": 0.9930556,
"backgroundColor": [ "#e31a1c", "#6a3d9a", "#bebada", "#fb8072", "#b3de69", "#fccde5" ] 
},
"Intermediate": {
 "Drug": null,
"percentage": null 
},
"Resistant": {
 "Drug": {
 "Clindamycin": {
 "State": {
 "State": [ "N/A" ],
"percentage": [      100 ] 
},
"Gender": {
 "Gender": [ "Male" ],
"percentage": [      100 ] 
},
"Age.Group": {
 "Age.Group": [ "65 to 84 Years" ],
"percentage": [      100 ] 
},
"Speciality": {
 "Speciality": [ "Clinic / Office" ],
"percentage": [      100 ] 
},
"Source": {
 "Source": [ "INT: Wound" ],
"percentage": [      100 ] 
},
"In...Out.Patient": {
 "In...Out.Patient": [ "Outpatient" ],
"percentage": [      100 ] 
} 
} 
},
"percentage":      100,
"weight": 0.006944444,
"backgroundColor": "#6a3d9a" 
} 
}
