{
 "Susceptible": {
 "Drug": {
 "Amikacin": {
 "State": {
 "State": [ "N/A" ],
"percentage": [      100 ] 
},
"Gender": {
 "Gender": [ "Female", "Male" ],
"percentage": [ 27.27273, 72.72727 ] 
},
"Age.Group": {
 "Age.Group": [ "0 to 2 Years", "19 to 64 Years", "65 to 84 Years" ],
"percentage": [ 9.090909, 45.45455, 45.45455 ] 
},
"Speciality": {
 "Speciality": [ "Medicine General", "Medicine ICU", "None Given", "Pediatric ICU", "Surgery General", "Surgery ICU" ],
"percentage": [ 27.27273, 9.090909, 18.18182, 9.090909, 18.18182, 18.18182 ] 
},
"Source": {
 "Source": [ "Bodily Fluids: Abscess / Pus", "CVS: Blood", "GU: Urine", "INT: Burn", "INT: Wound", "None Given" ],
"percentage": [ 9.090909, 9.090909, 36.36364, 27.27273, 9.090909, 9.090909 ] 
},
"In...Out.Patient": {
 "In...Out.Patient": [ "Inpatient", "None Given" ],
"percentage": [ 81.81818, 18.18182 ] 
} 
},
"Cefepime": {
 "State": {
 "State": [ "N/A" ],
"percentage": [      100 ] 
},
"Gender": {
 "Gender": [ "Female", "Male" ],
"percentage": [       20,       80 ] 
},
"Age.Group": {
 "Age.Group": [ "0 to 2 Years", "19 to 64 Years", "65 to 84 Years" ],
"percentage": [       10,       40,       50 ] 
},
"Speciality": {
 "Speciality": [ "Medicine General", "None Given", "Pediatric ICU", "Surgery General", "Surgery ICU" ],
"percentage": [       20,       10,       10,       50,       10 ] 
},
"Source": {
 "Source": [ "CVS: Blood", "GU: Urine", "INT: Burn", "INT: Wound", "None Given", "Skeletal: Bone" ],
"percentage": [       10,       20,       20,       30,       10,       10 ] 
},
"In...Out.Patient": {
 "In...Out.Patient": [ "Inpatient", "None Given" ],
"percentage": [       90,       10 ] 
} 
},
"Ceftazidime": {
 "State": {
 "State": [ "N/A" ],
"percentage": [      100 ] 
},
"Gender": {
 "Gender": [ "Female", "Male" ],
"percentage": [       40,       60 ] 
},
"Age.Group": {
 "Age.Group": [ "0 to 2 Years", "19 to 64 Years", "65 to 84 Years" ],
"percentage": [       20,       20,       60 ] 
},
"Speciality": {
 "Speciality": [ "Medicine General", "None Given", "Pediatric ICU", "Surgery General" ],
"percentage": [       40,       20,       20,       20 ] 
},
"Source": {
 "Source": [ "CVS: Blood", "GU: Urine", "INT: Wound" ],
"percentage": [       20,       40,       40 ] 
},
"In...Out.Patient": {
 "In...Out.Patient": [ "Inpatient", "None Given" ],
"percentage": [       80,       20 ] 
} 
},
"Ceftriaxone": {
 "State": {
 "State": [ "N/A" ],
"percentage": [      100 ] 
},
"Gender": {
 "Gender": [ "Male" ],
"percentage": [      100 ] 
},
"Age.Group": {
 "Age.Group": [ "65 to 84 Years" ],
"percentage": [      100 ] 
},
"Speciality": {
 "Speciality": [ "None Given", "Surgery General" ],
"percentage": [       50,       50 ] 
},
"Source": {
 "Source": [ "GU: Urine", "INT: Wound" ],
"percentage": [       50,       50 ] 
},
"In...Out.Patient": {
 "In...Out.Patient": [ "Inpatient", "None Given" ],
"percentage": [       50,       50 ] 
} 
},
"Levofloxacin": {
 "State": {
 "State": [ "N/A" ],
"percentage": [      100 ] 
},
"Gender": {
 "Gender": [ "Female", "Male" ],
"percentage": [       75,       25 ] 
},
"Age.Group": {
 "Age.Group": [ "0 to 2 Years", "19 to 64 Years", "65 to 84 Years" ],
"percentage": [ 8.333333, 58.33333, 33.33333 ] 
},
"Speciality": {
 "Speciality": [ "Medicine General", "None Given", "Pediatric ICU", "Surgery General" ],
"percentage": [ 16.66667, 58.33333, 8.333333, 16.66667 ] 
},
"Source": {
 "Source": [ "CVS: Blood", "GU: Urine", "INT: Wound", "Reproductive: Vagina", "Skeletal: Bone" ],
"percentage": [ 16.66667,       25, 8.333333, 41.66667, 8.333333 ] 
},
"In...Out.Patient": {
 "In...Out.Patient": [ "Inpatient", "None Given" ],
"percentage": [ 41.66667, 58.33333 ] 
} 
},
"Meropenem": {
 "State": {
 "State": [ "N/A" ],
"percentage": [      100 ] 
},
"Gender": {
 "Gender": [ "Female", "Male" ],
"percentage": [       10,       90 ] 
},
"Age.Group": {
 "Age.Group": [ "0 to 2 Years", "19 to 64 Years", "3 to 12 Years", "65 to 84 Years" ],
"percentage": [       10,       10,       10,       70 ] 
},
"Speciality": {
 "Speciality": [ "Medicine General", "Medicine ICU", "None Given", "Pediatric ICU", "Surgery General" ],
"percentage": [       30,       10,       10,       20,       30 ] 
},
"Source": {
 "Source": [ "Bodily Fluids: Abscess / Pus", "CVS: Blood", "GU: Urine", "Integumentary (INT)", "INT: Wound", "None Given" ],
"percentage": [       20,       10,       30,       10,       20,       10 ] 
},
"In...Out.Patient": {
 "In...Out.Patient": [ "Inpatient", "None Given" ],
"percentage": [       90,       10 ] 
} 
},
"Minocycline": {
 "State": {
 "State": [ "N/A" ],
"percentage": [      100 ] 
},
"Gender": {
 "Gender": [ "Female", "Male", "Not recorded" ],
"percentage": [ 39.53488, 58.13953, 2.325581 ] 
},
"Age.Group": {
 "Age.Group": [ "0 to 2 Years", "19 to 64 Years", "3 to 12 Years", "65 to 84 Years" ],
"percentage": [ 4.651163, 51.16279, 2.325581, 41.86047 ] 
},
"Speciality": {
 "Speciality": [ "Medicine General", "Medicine ICU", "None Given", "Pediatric General", "Pediatric ICU", "Surgery General", "Surgery ICU" ],
"percentage": [ 18.60465, 27.90698, 18.60465, 2.325581, 4.651163, 23.25581, 4.651163 ] 
},
"Source": {
 "Source": [ "Bodily Fluids: Abscess / Pus", "CVS: Blood", "GU: Urine", "Instruments: Catheters", "INT: Burn", "INT: Wound", "None Given", "Reproductive: Vagina", "Respiratory: Bronchials", "Respiratory: Sputum", "Skeletal: Bone" ],
"percentage": [ 9.302326, 16.27907, 9.302326, 6.976744, 4.651163, 16.27907, 2.325581, 11.62791, 9.302326, 2.325581, 11.62791 ] 
},
"In...Out.Patient": {
 "In...Out.Patient": [ "Inpatient", "None Given" ],
"percentage": [ 81.39535, 18.60465 ] 
} 
},
"Piperacillin tazobactam": {
 "State": {
 "State": [ "N/A" ],
"percentage": [      100 ] 
},
"Gender": {
 "Gender": [ "Male" ],
"percentage": [      100 ] 
},
"Age.Group": {
 "Age.Group": [ "0 to 2 Years", "65 to 84 Years" ],
"percentage": [ 33.33333, 66.66667 ] 
},
"Speciality": {
 "Speciality": [ "None Given", "Pediatric ICU", "Surgery General" ],
"percentage": [ 33.33333, 33.33333, 33.33333 ] 
},
"Source": {
 "Source": [ "CVS: Blood", "GU: Urine", "INT: Wound" ],
"percentage": [ 33.33333, 33.33333, 33.33333 ] 
},
"In...Out.Patient": {
 "In...Out.Patient": [ "Inpatient", "None Given" ],
"percentage": [ 66.66667, 33.33333 ] 
} 
} 
},
"percentage": [ 11.45833, 10.41667, 5.208333, 2.083333,     12.5, 10.41667, 44.79167,    3.125 ],
"weight": 0.2105263,
"backgroundColor": [ "#a6cee3", "#fb9a99", "#fdbf6f", "#ff7f00", "#8dd3c7", "#bebada", "#80b1d3", "#b3de69" ] 
},
"Intermediate": {
 "Drug": {
 "Cefepime": {
 "State": {
 "State": [ "N/A" ],
"percentage": [      100 ] 
},
"Gender": {
 "Gender": [ "Female", "Male" ],
"percentage": [       50,       50 ] 
},
"Age.Group": {
 "Age.Group": [ "19 to 64 Years", "3 to 12 Years", "65 to 84 Years" ],
"percentage": [       50,       25,       25 ] 
},
"Speciality": {
 "Speciality": [ "Medicine General", "None Given", "Pediatric ICU", "Surgery General" ],
"percentage": [       25,       25,       25,       25 ] 
},
"Source": {
 "Source": [ "GU: Urine", "Integumentary (INT)", "INT: Wound" ],
"percentage": [       25,       25,       50 ] 
},
"In...Out.Patient": {
 "In...Out.Patient": [ "Inpatient", "None Given" ],
"percentage": [       75,       25 ] 
} 
},
"Ceftazidime": {
 "State": {
 "State": [ "N/A" ],
"percentage": [      100 ] 
},
"Gender": {
 "Gender": [ "Female", "Male" ],
"percentage": [ 66.66667, 33.33333 ] 
},
"Age.Group": {
 "Age.Group": [ "19 to 64 Years", "65 to 84 Years" ],
"percentage": [ 88.88889, 11.11111 ] 
},
"Speciality": {
 "Speciality": [ "Medicine General", "None Given", "Surgery General", "Surgery ICU" ],
"percentage": [ 11.11111, 55.55556, 22.22222, 11.11111 ] 
},
"Source": {
 "Source": [ "GU: Urine", "INT: Burn", "None Given", "Reproductive: Vagina", "Skeletal: Bone" ],
"percentage": [ 11.11111, 22.22222, 11.11111, 44.44444, 11.11111 ] 
},
"In...Out.Patient": {
 "In...Out.Patient": [ "Inpatient", "None Given" ],
"percentage": [ 44.44444, 55.55556 ] 
} 
},
"Ceftriaxone": {
 "State": {
 "State": [ "N/A" ],
"percentage": [      100 ] 
},
"Gender": {
 "Gender": [ "Female", "Male" ],
"percentage": [ 33.33333, 66.66667 ] 
},
"Age.Group": {
 "Age.Group": [ "0 to 2 Years", "19 to 64 Years", "65 to 84 Years" ],
"percentage": [ 33.33333, 33.33333, 33.33333 ] 
},
"Speciality": {
 "Speciality": [ "Medicine General", "Pediatric ICU", "Surgery ICU" ],
"percentage": [ 33.33333, 33.33333, 33.33333 ] 
},
"Source": {
 "Source": [ "CVS: Blood", "GU: Urine", "INT: Burn" ],
"percentage": [ 33.33333, 33.33333, 33.33333 ] 
},
"In...Out.Patient": {
 "In...Out.Patient": [ "Inpatient" ],
"percentage": [      100 ] 
} 
},
"Levofloxacin": {
 "State": {
 "State": [ "N/A" ],
"percentage": [      100 ] 
},
"Gender": {
 "Gender": [ "Female", "Male", "Not recorded" ],
"percentage": [ 23.52941, 70.58824, 5.882353 ] 
},
"Age.Group": {
 "Age.Group": [ "0 to 2 Years", "19 to 64 Years", "3 to 12 Years", "65 to 84 Years" ],
"percentage": [ 5.882353, 47.05882, 5.882353, 41.17647 ] 
},
"Speciality": {
 "Speciality": [ "Medicine General", "Medicine ICU", "Pediatric General", "Pediatric ICU", "Surgery General", "Surgery ICU" ],
"percentage": [ 11.76471, 41.17647, 5.882353, 5.882353, 29.41176, 5.882353 ] 
},
"Source": {
 "Source": [ "Bodily Fluids: Abscess / Pus", "CVS: Blood", "INT: Wound", "None Given", "Respiratory: Bronchials", "Skeletal: Bone" ],
"percentage": [ 23.52941, 17.64706, 23.52941, 5.882353, 11.76471, 17.64706 ] 
},
"In...Out.Patient": {
 "In...Out.Patient": [ "Inpatient" ],
"percentage": [      100 ] 
} 
},
"Meropenem": {
 "State": {
 "State": [ "N/A" ],
"percentage": [      100 ] 
},
"Gender": {
 "Gender": [ "Female" ],
"percentage": [      100 ] 
},
"Age.Group": {
 "Age.Group": [ "65 to 84 Years" ],
"percentage": [      100 ] 
},
"Speciality": {
 "Speciality": [ "Medicine General", "None Given" ],
"percentage": [       50,       50 ] 
},
"Source": {
 "Source": [ "GU: Urine", "Instruments: Catheters" ],
"percentage": [       50,       50 ] 
},
"In...Out.Patient": {
 "In...Out.Patient": [ "Inpatient", "None Given" ],
"percentage": [       50,       50 ] 
} 
},
"Minocycline": {
 "State": {
 "State": [ "N/A" ],
"percentage": [      100 ] 
},
"Gender": {
 "Gender": [ "Female", "Male" ],
"percentage": [       25,       75 ] 
},
"Age.Group": {
 "Age.Group": [ "19 to 64 Years", "65 to 84 Years" ],
"percentage": [       50,       50 ] 
},
"Speciality": {
 "Speciality": [ "Medicine General", "Medicine ICU", "Surgery General", "Surgery ICU" ],
"percentage": [       25,       50,     12.5,     12.5 ] 
},
"Source": {
 "Source": [ "Instruments: Catheters", "INT: Burn", "Integumentary (INT)", "INT: Wound", "Respiratory: Bronchials", "Respiratory: Trachea" ],
"percentage": [     12.5,     12.5,     12.5,     12.5,     37.5,     12.5 ] 
},
"In...Out.Patient": {
 "In...Out.Patient": [ "Inpatient" ],
"percentage": [      100 ] 
} 
},
"Piperacillin tazobactam": {
 "State": {
 "State": [ "N/A" ],
"percentage": [      100 ] 
},
"Gender": {
 "Gender": [ "Female", "Male" ],
"percentage": [ 66.66667, 33.33333 ] 
},
"Age.Group": {
 "Age.Group": [ "65 to 84 Years" ],
"percentage": [      100 ] 
},
"Speciality": {
 "Speciality": [ "Medicine General" ],
"percentage": [      100 ] 
},
"Source": {
 "Source": [ "GU: Urine", "Integumentary (INT)" ],
"percentage": [ 66.66667, 33.33333 ] 
},
"In...Out.Patient": {
 "In...Out.Patient": [ "Inpatient" ],
"percentage": [      100 ] 
} 
} 
},
"percentage": [ 8.695652, 19.56522, 6.521739, 36.95652, 4.347826,  17.3913, 6.521739 ],
"weight": 0.1008772,
"backgroundColor": [ "#fb9a99", "#fdbf6f", "#ff7f00", "#8dd3c7", "#bebada", "#80b1d3", "#b3de69" ] 
},
"Resistant": {
 "Drug": {
 "Amikacin": {
 "State": {
 "State": [ "N/A" ],
"percentage": [      100 ] 
},
"Gender": {
 "Gender": [ "Female", "Male", "Not recorded" ],
"percentage": [ 41.30435, 56.52174, 2.173913 ] 
},
"Age.Group": {
 "Age.Group": [ "0 to 2 Years", "19 to 64 Years", "3 to 12 Years", "65 to 84 Years" ],
"percentage": [ 2.173913, 54.34783, 2.173913, 41.30435 ] 
},
"Speciality": {
 "Speciality": [ "Medicine General", "Medicine ICU", "None Given", "Pediatric General", "Pediatric ICU", "Surgery General", "Surgery ICU" ],
"percentage": [  17.3913, 34.78261, 15.21739, 2.173913, 2.173913, 23.91304, 4.347826 ] 
},
"Source": {
 "Source": [ "Bodily Fluids: Abscess / Pus", "CVS: Blood", "GU: Urine", "Instruments: Catheters", "INT: Burn", "Integumentary (INT)", "INT: Wound", "Reproductive: Vagina", "Respiratory: Bronchials", "Respiratory: Sputum", "Respiratory: Trachea", "Skeletal: Bone" ],
"percentage": [ 6.521739, 15.21739, 4.347826, 8.695652, 2.173913, 2.173913, 19.56522, 10.86957, 15.21739, 2.173913, 2.173913, 10.86957 ] 
},
"In...Out.Patient": {
 "In...Out.Patient": [ "Inpatient", "None Given" ],
"percentage": [ 84.78261, 15.21739 ] 
} 
},
"Cefepime": {
 "State": {
 "State": [ "N/A" ],
"percentage": [      100 ] 
},
"Gender": {
 "Gender": [ "Female", "Male", "Not recorded" ],
"percentage": [ 41.86047, 55.81395, 2.325581 ] 
},
"Age.Group": {
 "Age.Group": [ "0 to 2 Years", "19 to 64 Years", "65 to 84 Years" ],
"percentage": [ 2.325581, 55.81395, 41.86047 ] 
},
"Speciality": {
 "Speciality": [ "Medicine General", "Medicine ICU", "None Given", "Pediatric General", "Surgery General", "Surgery ICU" ],
"percentage": [ 18.60465, 39.53488, 16.27907, 2.325581, 16.27907, 6.976744 ] 
},
"Source": {
 "Source": [ "Bodily Fluids: Abscess / Pus", "CVS: Blood", "GU: Urine", "Instruments: Catheters", "INT: Burn", "INT: Wound", "Reproductive: Vagina", "Respiratory: Bronchials", "Respiratory: Sputum", "Respiratory: Trachea", "Skeletal: Bone" ],
"percentage": [ 9.302326, 16.27907, 6.976744, 9.302326, 4.651163, 11.62791, 11.62791, 16.27907, 2.325581, 2.325581, 9.302326 ] 
},
"In...Out.Patient": {
 "In...Out.Patient": [ "Inpatient", "None Given" ],
"percentage": [ 83.72093, 16.27907 ] 
} 
},
"Ceftazidime": {
 "State": {
 "State": [ "N/A" ],
"percentage": [      100 ] 
},
"Gender": {
 "Gender": [ "Female", "Male", "Not recorded" ],
"percentage": [ 32.55814, 65.11628, 2.325581 ] 
},
"Age.Group": {
 "Age.Group": [ "0 to 2 Years", "19 to 64 Years", "3 to 12 Years", "65 to 84 Years" ],
"percentage": [ 2.325581, 48.83721, 2.325581, 46.51163 ] 
},
"Speciality": {
 "Speciality": [ "Medicine General", "Medicine ICU", "None Given", "Pediatric General", "Pediatric ICU", "Surgery General", "Surgery ICU" ],
"percentage": [ 18.60465, 39.53488, 6.976744, 2.325581, 2.325581, 23.25581, 6.976744 ] 
},
"Source": {
 "Source": [ "Bodily Fluids: Abscess / Pus", "CVS: Blood", "GU: Urine", "Instruments: Catheters", "INT: Burn", "Integumentary (INT)", "INT: Wound", "Reproductive: Vagina", "Respiratory: Bronchials", "Respiratory: Sputum", "Respiratory: Trachea", "Skeletal: Bone" ],
"percentage": [ 9.302326, 16.27907, 6.976744, 9.302326, 4.651163, 2.325581, 18.60465, 2.325581, 16.27907, 2.325581, 2.325581, 9.302326 ] 
},
"In...Out.Patient": {
 "In...Out.Patient": [ "Inpatient", "None Given" ],
"percentage": [ 93.02326, 6.976744 ] 
} 
},
"Ceftriaxone": {
 "State": {
 "State": [ "N/A" ],
"percentage": [      100 ] 
},
"Gender": {
 "Gender": [ "Female", "Male", "Not recorded" ],
"percentage": [ 40.38462, 57.69231, 1.923077 ] 
},
"Age.Group": {
 "Age.Group": [ "0 to 2 Years", "19 to 64 Years", "3 to 12 Years", "65 to 84 Years" ],
"percentage": [ 1.923077, 55.76923, 1.923077, 40.38462 ] 
},
"Speciality": {
 "Speciality": [ "Medicine General", "Medicine ICU", "None Given", "Pediatric General", "Pediatric ICU", "Surgery General", "Surgery ICU" ],
"percentage": [ 19.23077, 32.69231, 15.38462, 1.923077, 1.923077, 23.07692, 5.769231 ] 
},
"Source": {
 "Source": [ "Bodily Fluids: Abscess / Pus", "CVS: Blood", "GU: Urine", "Instruments: Catheters", "INT: Burn", "Integumentary (INT)", "INT: Wound", "None Given", "Reproductive: Vagina", "Respiratory: Bronchials", "Respiratory: Sputum", "Respiratory: Trachea", "Skeletal: Bone" ],
"percentage": [ 7.692308, 13.46154, 7.692308, 7.692308, 5.769231, 1.923077, 17.30769, 1.923077, 9.615385, 13.46154, 1.923077, 1.923077, 9.615385 ] 
},
"In...Out.Patient": {
 "In...Out.Patient": [ "Inpatient", "None Given" ],
"percentage": [ 84.61538, 15.38462 ] 
} 
},
"Levofloxacin": {
 "State": {
 "State": [ "N/A" ],
"percentage": [      100 ] 
},
"Gender": {
 "Gender": [ "Female", "Male" ],
"percentage": [ 32.14286, 67.85714 ] 
},
"Age.Group": {
 "Age.Group": [ "19 to 64 Years", "65 to 84 Years" ],
"percentage": [ 53.57143, 46.42857 ] 
},
"Speciality": {
 "Speciality": [ "Medicine General", "Medicine ICU", "None Given", "Surgery General", "Surgery ICU" ],
"percentage": [       25, 35.71429, 7.142857, 21.42857, 10.71429 ] 
},
"Source": {
 "Source": [ "CVS: Blood", "GU: Urine", "Instruments: Catheters", "INT: Burn", "Integumentary (INT)", "INT: Wound", "Respiratory: Bronchials", "Respiratory: Sputum", "Respiratory: Trachea", "Skeletal: Bone" ],
"percentage": [ 10.71429, 10.71429, 14.28571, 14.28571, 3.571429, 17.85714, 17.85714, 3.571429, 3.571429, 3.571429 ] 
},
"In...Out.Patient": {
 "In...Out.Patient": [ "Inpatient", "None Given" ],
"percentage": [ 92.85714, 7.142857 ] 
} 
},
"Meropenem": {
 "State": {
 "State": [ "N/A" ],
"percentage": [      100 ] 
},
"Gender": {
 "Gender": [ "Female", "Male", "Not recorded" ],
"percentage": [ 42.22222, 55.55556, 2.222222 ] 
},
"Age.Group": {
 "Age.Group": [ "0 to 2 Years", "19 to 64 Years", "65 to 84 Years" ],
"percentage": [ 2.222222, 64.44444, 33.33333 ] 
},
"Speciality": {
 "Speciality": [ "Medicine General", "Medicine ICU", "None Given", "Pediatric General", "Surgery General", "Surgery ICU" ],
"percentage": [ 15.55556, 35.55556, 15.55556, 2.222222, 22.22222, 8.888889 ] 
},
"Source": {
 "Source": [ "Bodily Fluids: Abscess / Pus", "CVS: Blood", "GU: Urine", "Instruments: Catheters", "INT: Burn", "INT: Wound", "Reproductive: Vagina", "Respiratory: Bronchials", "Respiratory: Sputum", "Respiratory: Trachea", "Skeletal: Bone" ],
"percentage": [ 4.444444, 15.55556, 4.444444, 6.666667, 8.888889, 17.77778, 11.11111, 15.55556, 2.222222, 2.222222, 11.11111 ] 
},
"In...Out.Patient": {
 "In...Out.Patient": [ "Inpatient", "None Given" ],
"percentage": [ 84.44444, 15.55556 ] 
} 
},
"Minocycline": {
 "State": {
 "State": [ "N/A" ],
"percentage": [      100 ] 
},
"Gender": {
 "Gender": [ "Female", "Male" ],
"percentage": [       50,       50 ] 
},
"Age.Group": {
 "Age.Group": [ "19 to 64 Years", "65 to 84 Years" ],
"percentage": [ 66.66667, 33.33333 ] 
},
"Speciality": {
 "Speciality": [ "Medicine General", "Medicine ICU", "None Given", "Surgery General", "Surgery ICU" ],
"percentage": [ 16.66667, 16.66667, 16.66667, 33.33333, 16.66667 ] 
},
"Source": {
 "Source": [ "CVS: Blood", "GU: Urine", "INT: Burn", "INT: Wound" ],
"percentage": [ 16.66667, 33.33333, 16.66667, 33.33333 ] 
},
"In...Out.Patient": {
 "In...Out.Patient": [ "Inpatient", "None Given" ],
"percentage": [ 83.33333, 16.66667 ] 
} 
},
"Piperacillin tazobactam": {
 "State": {
 "State": [ "N/A" ],
"percentage": [      100 ] 
},
"Gender": {
 "Gender": [ "Female", "Male", "Not recorded" ],
"percentage": [ 39.21569, 58.82353, 1.960784 ] 
},
"Age.Group": {
 "Age.Group": [ "0 to 2 Years", "19 to 64 Years", "3 to 12 Years", "65 to 84 Years" ],
"percentage": [ 1.960784, 58.82353, 1.960784,  37.2549 ] 
},
"Speciality": {
 "Speciality": [ "Medicine General", "Medicine ICU", "None Given", "Pediatric General", "Pediatric ICU", "Surgery General", "Surgery ICU" ],
"percentage": [ 15.68627, 33.33333, 15.68627, 1.960784, 1.960784, 23.52941, 7.843137 ] 
},
"Source": {
 "Source": [ "Bodily Fluids: Abscess / Pus", "CVS: Blood", "GU: Urine", "Instruments: Catheters", "INT: Burn", "INT: Wound", "None Given", "Reproductive: Vagina", "Respiratory: Bronchials", "Respiratory: Sputum", "Respiratory: Trachea", "Skeletal: Bone" ],
"percentage": [ 7.843137, 13.72549, 5.882353, 7.843137, 7.843137, 17.64706, 1.960784, 9.803922, 13.72549, 1.960784, 1.960784, 9.803922 ] 
},
"In...Out.Patient": {
 "In...Out.Patient": [ "Inpatient", "None Given" ],
"percentage": [ 84.31373, 15.68627 ] 
} 
} 
},
"percentage": [ 14.64968, 13.69427, 13.69427, 16.56051, 8.917197, 14.33121, 1.910828, 16.24204 ],
"weight": 0.6885965,
"backgroundColor": [ "#a6cee3", "#fb9a99", "#fdbf6f", "#ff7f00", "#8dd3c7", "#bebada", "#80b1d3", "#b3de69" ] 
} 
}
