{
 "Susceptible": {
 "Drug": {
 "Amikacin": {
 "State": {
 "State": [ "N/A" ],
"percentage": [      100 ] 
},
"Gender": {
 "Gender": [ "Female", "Male", "Not recorded" ],
"percentage": [ 26.31579, 68.42105, 5.263158 ] 
},
"Age.Group": {
 "Age.Group": [ "19 to 64 Years", "65 to 84 Years", "85 and Over" ],
"percentage": [ 36.84211, 36.84211, 26.31579 ] 
},
"Speciality": {
 "Speciality": [ "Medicine General", "Medicine ICU", "None Given", "Surgery ICU" ],
"percentage": [ 78.94737, 10.52632, 5.263158, 5.263158 ] 
},
"Source": {
 "Source": [ "Bodily Fluids: Abdominal", "CVS: Blood" ],
"percentage": [ 5.263158, 94.73684 ] 
},
"In...Out.Patient": {
 "In...Out.Patient": [ "Inpatient", "None Given" ],
"percentage": [ 94.73684, 5.263158 ] 
} 
},
"Cefepime": {
 "State": {
 "State": [ "N/A" ],
"percentage": [      100 ] 
},
"Gender": {
 "Gender": [ "Female", "Male", "Not recorded" ],
"percentage": [    31.25,     62.5,     6.25 ] 
},
"Age.Group": {
 "Age.Group": [ "19 to 64 Years", "65 to 84 Years", "85 and Over" ],
"percentage": [     37.5,     37.5,       25 ] 
},
"Speciality": {
 "Speciality": [ "Medicine General", "Medicine ICU", "None Given", "Surgery ICU" ],
"percentage": [       75,     12.5,     6.25,     6.25 ] 
},
"Source": {
 "Source": [ "CVS: Blood" ],
"percentage": [      100 ] 
},
"In...Out.Patient": {
 "In...Out.Patient": [ "Inpatient", "None Given" ],
"percentage": [    93.75,     6.25 ] 
} 
},
"Ceftazidime": {
 "State": {
 "State": [ "N/A" ],
"percentage": [      100 ] 
},
"Gender": {
 "Gender": [ "Female", "Male", "Not recorded" ],
"percentage": [ 23.52941, 70.58824, 5.882353 ] 
},
"Age.Group": {
 "Age.Group": [ "19 to 64 Years", "65 to 84 Years", "85 and Over" ],
"percentage": [ 41.17647, 29.41176, 29.41176 ] 
},
"Speciality": {
 "Speciality": [ "Medicine General", "Medicine ICU", "None Given", "Surgery ICU" ],
"percentage": [ 76.47059, 11.76471, 5.882353, 5.882353 ] 
},
"Source": {
 "Source": [ "CVS: Blood" ],
"percentage": [      100 ] 
},
"In...Out.Patient": {
 "In...Out.Patient": [ "Inpatient", "None Given" ],
"percentage": [ 94.11765, 5.882353 ] 
} 
},
"Levofloxacin": {
 "State": {
 "State": [ "N/A" ],
"percentage": [      100 ] 
},
"Gender": {
 "Gender": [ "Female", "Male", "Not recorded" ],
"percentage": [    31.25,     62.5,     6.25 ] 
},
"Age.Group": {
 "Age.Group": [ "19 to 64 Years", "65 to 84 Years", "85 and Over" ],
"percentage": [     37.5,     37.5,       25 ] 
},
"Speciality": {
 "Speciality": [ "Medicine General", "Medicine ICU", "None Given", "Surgery ICU" ],
"percentage": [       75,     12.5,     6.25,     6.25 ] 
},
"Source": {
 "Source": [ "CVS: Blood" ],
"percentage": [      100 ] 
},
"In...Out.Patient": {
 "In...Out.Patient": [ "Inpatient", "None Given" ],
"percentage": [    93.75,     6.25 ] 
} 
},
"Meropenem": {
 "State": {
 "State": [ "N/A" ],
"percentage": [      100 ] 
},
"Gender": {
 "Gender": [ "Female", "Male", "Not recorded" ],
"percentage": [ 28.57143, 64.28571, 7.142857 ] 
},
"Age.Group": {
 "Age.Group": [ "19 to 64 Years", "65 to 84 Years", "85 and Over" ],
"percentage": [ 28.57143,       50, 21.42857 ] 
},
"Speciality": {
 "Speciality": [ "Medicine General", "Medicine ICU", "None Given" ],
"percentage": [ 85.71429, 7.142857, 7.142857 ] 
},
"Source": {
 "Source": [ "CVS: Blood" ],
"percentage": [      100 ] 
},
"In...Out.Patient": {
 "In...Out.Patient": [ "Inpatient", "None Given" ],
"percentage": [ 92.85714, 7.142857 ] 
} 
},
"Piperacillin tazobactam": {
 "State": {
 "State": [ "N/A" ],
"percentage": [      100 ] 
},
"Gender": {
 "Gender": [ "Female", "Male", "Not recorded" ],
"percentage": [ 27.77778, 66.66667, 5.555556 ] 
},
"Age.Group": {
 "Age.Group": [ "19 to 64 Years", "65 to 84 Years", "85 and Over" ],
"percentage": [ 44.44444, 33.33333, 22.22222 ] 
},
"Speciality": {
 "Speciality": [ "Medicine General", "Medicine ICU", "None Given", "Surgery ICU" ],
"percentage": [ 77.77778, 11.11111, 5.555556, 5.555556 ] 
},
"Source": {
 "Source": [ "Bodily Fluids: Abdominal", "CVS: Blood" ],
"percentage": [ 5.555556, 94.44444 ] 
},
"In...Out.Patient": {
 "In...Out.Patient": [ "Inpatient", "None Given" ],
"percentage": [ 94.44444, 5.555556 ] 
} 
} 
},
"percentage": [       19,       16,       17,       16,       14,       18 ],
"weight": 0.8333333,
"backgroundColor": [ "#a6cee3", "#fb9a99", "#fdbf6f", "#8dd3c7", "#bebada", "#b3de69" ] 
},
"Intermediate": {
 "Drug": {
 "Amikacin": {
 "State": {
 "State": [ "N/A" ],
"percentage": [      100 ] 
},
"Gender": {
 "Gender": [ "Male" ],
"percentage": [      100 ] 
},
"Age.Group": {
 "Age.Group": [ "19 to 64 Years" ],
"percentage": [      100 ] 
},
"Speciality": {
 "Speciality": [ "Medicine General" ],
"percentage": [      100 ] 
},
"Source": {
 "Source": [ "CVS: Blood" ],
"percentage": [      100 ] 
},
"In...Out.Patient": {
 "In...Out.Patient": [ "Inpatient" ],
"percentage": [      100 ] 
} 
},
"Cefepime": {
 "State": {
 "State": [ "N/A" ],
"percentage": [      100 ] 
},
"Gender": {
 "Gender": [ "Male" ],
"percentage": [      100 ] 
},
"Age.Group": {
 "Age.Group": [ "19 to 64 Years", "65 to 84 Years" ],
"percentage": [       50,       50 ] 
},
"Speciality": {
 "Speciality": [ "Medicine General" ],
"percentage": [      100 ] 
},
"Source": {
 "Source": [ "CVS: Blood" ],
"percentage": [      100 ] 
},
"In...Out.Patient": {
 "In...Out.Patient": [ "Inpatient" ],
"percentage": [      100 ] 
} 
},
"Ceftazidime": {
 "State": {
 "State": [ "N/A" ],
"percentage": [      100 ] 
},
"Gender": {
 "Gender": [ "Female", "Male" ],
"percentage": [       50,       50 ] 
},
"Age.Group": {
 "Age.Group": [ "65 to 84 Years" ],
"percentage": [      100 ] 
},
"Speciality": {
 "Speciality": [ "Medicine General" ],
"percentage": [      100 ] 
},
"Source": {
 "Source": [ "CVS: Blood" ],
"percentage": [      100 ] 
},
"In...Out.Patient": {
 "In...Out.Patient": [ "Inpatient" ],
"percentage": [      100 ] 
} 
},
"Meropenem": {
 "State": {
 "State": [ "N/A" ],
"percentage": [      100 ] 
},
"Gender": {
 "Gender": [ "Female", "Male" ],
"percentage": [       50,       50 ] 
},
"Age.Group": {
 "Age.Group": [ "19 to 64 Years", "85 and Over" ],
"percentage": [       50,       50 ] 
},
"Speciality": {
 "Speciality": [ "Medicine ICU", "Surgery ICU" ],
"percentage": [       50,       50 ] 
},
"Source": {
 "Source": [ "CVS: Blood" ],
"percentage": [      100 ] 
},
"In...Out.Patient": {
 "In...Out.Patient": [ "Inpatient" ],
"percentage": [      100 ] 
} 
},
"Piperacillin tazobactam": {
 "State": {
 "State": [ "N/A" ],
"percentage": [      100 ] 
},
"Gender": {
 "Gender": [ "Male" ],
"percentage": [      100 ] 
},
"Age.Group": {
 "Age.Group": [ "85 and Over" ],
"percentage": [      100 ] 
},
"Speciality": {
 "Speciality": [ "Medicine General" ],
"percentage": [      100 ] 
},
"Source": {
 "Source": [ "CVS: Blood" ],
"percentage": [      100 ] 
},
"In...Out.Patient": {
 "In...Out.Patient": [ "Inpatient" ],
"percentage": [      100 ] 
} 
} 
},
"percentage": [     12.5,       25,       25,       25,     12.5 ],
"weight": 0.06666667,
"backgroundColor": [ "#a6cee3", "#fb9a99", "#fdbf6f", "#bebada", "#b3de69" ] 
},
"Resistant": {
 "Drug": {
 "Cefepime": {
 "State": {
 "State": [ "N/A" ],
"percentage": [      100 ] 
},
"Gender": {
 "Gender": [ "Male" ],
"percentage": [      100 ] 
},
"Age.Group": {
 "Age.Group": [ "19 to 64 Years", "85 and Over" ],
"percentage": [       50,       50 ] 
},
"Speciality": {
 "Speciality": [ "Medicine General" ],
"percentage": [      100 ] 
},
"Source": {
 "Source": [ "Bodily Fluids: Abdominal", "CVS: Blood" ],
"percentage": [       50,       50 ] 
},
"In...Out.Patient": {
 "In...Out.Patient": [ "Inpatient" ],
"percentage": [      100 ] 
} 
},
"Ceftazidime": {
 "State": {
 "State": [ "N/A" ],
"percentage": [      100 ] 
},
"Gender": {
 "Gender": [ "Male" ],
"percentage": [      100 ] 
},
"Age.Group": {
 "Age.Group": [ "19 to 64 Years" ],
"percentage": [      100 ] 
},
"Speciality": {
 "Speciality": [ "Medicine General" ],
"percentage": [      100 ] 
},
"Source": {
 "Source": [ "Bodily Fluids: Abdominal" ],
"percentage": [      100 ] 
},
"In...Out.Patient": {
 "In...Out.Patient": [ "Inpatient" ],
"percentage": [      100 ] 
} 
},
"Levofloxacin": {
 "State": {
 "State": [ "N/A" ],
"percentage": [      100 ] 
},
"Gender": {
 "Gender": [ "Male" ],
"percentage": [      100 ] 
},
"Age.Group": {
 "Age.Group": [ "19 to 64 Years", "65 to 84 Years", "85 and Over" ],
"percentage": [       50,       25,       25 ] 
},
"Speciality": {
 "Speciality": [ "Medicine General" ],
"percentage": [      100 ] 
},
"Source": {
 "Source": [ "Bodily Fluids: Abdominal", "CVS: Blood" ],
"percentage": [       25,       75 ] 
},
"In...Out.Patient": {
 "In...Out.Patient": [ "Inpatient" ],
"percentage": [      100 ] 
} 
},
"Meropenem": {
 "State": {
 "State": [ "N/A" ],
"percentage": [      100 ] 
},
"Gender": {
 "Gender": [ "Male" ],
"percentage": [      100 ] 
},
"Age.Group": {
 "Age.Group": [ "19 to 64 Years", "85 and Over" ],
"percentage": [       75,       25 ] 
},
"Speciality": {
 "Speciality": [ "Medicine General" ],
"percentage": [      100 ] 
},
"Source": {
 "Source": [ "Bodily Fluids: Abdominal", "CVS: Blood" ],
"percentage": [       25,       75 ] 
},
"In...Out.Patient": {
 "In...Out.Patient": [ "Inpatient" ],
"percentage": [      100 ] 
} 
},
"Piperacillin tazobactam": {
 "State": {
 "State": [ "N/A" ],
"percentage": [      100 ] 
},
"Gender": {
 "Gender": [ "Male" ],
"percentage": [      100 ] 
},
"Age.Group": {
 "Age.Group": [ "65 to 84 Years" ],
"percentage": [      100 ] 
},
"Speciality": {
 "Speciality": [ "Medicine General" ],
"percentage": [      100 ] 
},
"Source": {
 "Source": [ "CVS: Blood" ],
"percentage": [      100 ] 
},
"In...Out.Patient": {
 "In...Out.Patient": [ "Inpatient" ],
"percentage": [      100 ] 
} 
} 
},
"percentage": [ 16.66667, 8.333333, 33.33333, 33.33333, 8.333333 ],
"weight":      0.1,
"backgroundColor": [ "#fb9a99", "#fdbf6f", "#8dd3c7", "#bebada", "#b3de69" ] 
} 
}
